[{"name":"Aspen Dental","street":"15810 E Indiana Ave ","cityState":"Spokane Valley WA 99216-1864","phone":"Phone: (509) 795-3800","fax":"Fax: (509) 924-3072","webSite":"Website: "},{"name":"Sherman Family Dentistry","street":"15201 Shady Grove Road Suite 101","cityState":"Rockville MD 20850","phone":"Phone: (301) 840-0600","fax":"Fax: ","webSite":"Website: "},{"name":"Adam P Cormier Dds Apdc","street":"5839 E Kings Hwy ","cityState":"Shreveport LA 71105","phone":"Phone: (318) 868-4072","fax":"Fax: (318) 868-2019","webSite":"Website: "},{"name":"Dental Care Of Lacey","street":"719 Sleater Kinney Rd Se Ste 130 ","cityState":"Lacey WA 98503-1138","phone":"Phone: (360) 455-1231","fax":"Fax: (360) 455-1233","webSite":"Website: "},{"name":"Dental Care Of Sumner","street":"1006 Fryar Ave Suite B","cityState":"Sumner WA 98390-1501","phone":"Phone: (253) 863-2995","fax":"Fax: (253) 863-3821","webSite":"Website: "},{"name":"Smileshapers","street":"7945 W Sahara Ave Suite 101","cityState":"Las Vegas NV 89117-7908","phone":"Phone: (702) 220-7966","fax":"Fax: (702) 220-7926","webSite":"Website: "},{"name":"Carolina Center For Oral And Maxillofacial Surgery","street":"115 Powell Mill Rd ","cityState":"Spartanburg SC 29301-1531","phone":"Phone: (864) 574-2011","fax":"Fax: (864) 576-7377","webSite":"Website: "},{"name":"Adam R Dalesandro Pc","street":"762 N Country Club Rd ","cityState":"Tucson AZ 85716-4535","phone":"Phone: (520) 748-8004","fax":"Fax: (520) 327-0907","webSite":"Website: "},{"name":"Adam R Liberman Dmd","street":"7720 South Broadway Suite 430","cityState":"Littleton CO 80122","phone":"Phone: (303) 795-1443","fax":"Fax: (303) 795-1449","webSite":"Website: "},{"name":"Adam R Winckler Dds Pc","street":"950 N York Rd Suite 100","cityState":"Hinsdale IL 60521-2950","phone":"Phone: (630) 655-8815","fax":"Fax: (630) 655-8813","webSite":"Website: "},{"name":"Adam R. Pershing","street":"2300 N Craycroft Rd Ste 4 ","cityState":"Tucson AZ 85712-2808","phone":"Phone: (520) 722-2992","fax":"Fax: (520) 722-2993","webSite":"Website: "},{"name":"Adam Rauzman D.D.S.","street":"164 Warburton Ave ","cityState":"Hawthorne NJ 07506-2552","phone":"Phone: (973) 427-4201","fax":"Fax: ","webSite":"Website: "},{"name":"Adam S Colombo, Dds","street":"7301 Mission Rd Ste 317","cityState":"Prairie Village KS 66208-3006","phone":"Phone: (913) 236-7668","fax":"Fax: (913) 432-4520","webSite":"Website: "},{"name":"Adam Sumner Dmd Pllc","street":"5975 W Farm To Market Rd 78 #360 ","cityState":"San Antonio TX 78244","phone":"Phone: (210) 661-4212","fax":"Fax: ","webSite":"Website: "},{"name":"Adam T Clark Dds Dental Corporation","street":"26671 Aliso Creek Rd Suite 300","cityState":"Aliso Viejo CA 92656-4809","phone":"Phone: (949) 202-4480","fax":"Fax: ","webSite":"Website: "},{"name":"Hillsdale Dental","street":"127 Royal Troon Lane ","cityState":"Advance NC 27006-6651","phone":"Phone: (336) 998-2427","fax":"Fax: (336) 998-1088","webSite":"Website: "},{"name":"Adam Thompson Dmd Pllc","street":"203 Champion Way Suite #6","cityState":"Georgetown KY 40324-8861","phone":"Phone: (502) 868-5999","fax":"Fax: (502) 868-5944","webSite":"Website: "},{"name":"Adam Tyler Barnes, Dds Of Texas Ii, Pllc","street":"23225 Kingsland Blvd ","cityState":"Katy TX 77494-2890","phone":"Phone: (281) 395-0400","fax":"Fax: (281) 574-8840","webSite":"Website: "},{"name":"Adam Tyler Barnes, Dds Of Texas Ii, Pllc","street":"651 Fm 30009 250","cityState":"Schertz TX 78154","phone":"Phone: (210) 599-8700","fax":"Fax: (210) 599-1100","webSite":"Website: "},{"name":"Adam Tyler Barnes, Dds Of Texas Ii, Pllc","street":"11901 Shadow Creek Pkwy 135","cityState":"Pearland TX 77584-7346","phone":"Phone: (281) 372-6234","fax":"Fax: (281) 741-5847","webSite":"Website: "},{"name":"Adam Tyler Barnes, Dds Of Texas Ii, Pllc","street":"5715 W. I-20, Ste 111","cityState":"Arlington TX 76017","phone":"Phone: (817) 563-5615","fax":"Fax: ","webSite":"Website: "},{"name":"Adam Tyler Barnes, Dds Of Texas Ii, Pllc","street":"2415 S Austin Ave Ste 101 ","cityState":"Denison TX 75020-7742","phone":"Phone: (903) 327-8540","fax":"Fax: ","webSite":"Website: "},{"name":"Adam Tyler Barnes, Dds Of Texas Ii, Pllc","street":"510 N Loop 340 Ste E","cityState":"Bellmead TX 76705","phone":"Phone: (254) 267-5370","fax":"Fax: ","webSite":"Website: "},{"name":"Adam Tyler Barnes, Dds Of Texas Ii, Pllc","street":"2305 Longmire Dr Ste 70 ","cityState":"College Station TX 77845-7033","phone":"Phone: (979) 977-0047","fax":"Fax: ","webSite":"Website: "},{"name":"Adam Tyler Barnes, Dds Of Texas Ii, Pllc","street":"1142 West Dallas ","cityState":"Conroe TX 74430","phone":"Phone: (936) 760-1132","fax":"Fax: (936) 760-2941","webSite":"Website: "},{"name":"Adam Tyler Barnes, Dds Of Texas Ii, Pllc","street":"1700 N Highway 77 Ste 200 ","cityState":"Waxahachie TX 75165-7831","phone":"Phone: (972) 833-4994","fax":"Fax: ","webSite":"Website: "},{"name":"Adam Tyler Barnes, Dds Of Texas Ii, Pllc","street":"5892B Eastex Fwy ","cityState":"Beaumont TX 77708-4824","phone":"Phone: (409) 892-2991","fax":"Fax: ","webSite":"Website: "},{"name":"Adam Tyler Barnes, Dds Of Texas Ii, Pllc","street":"1103 Rivery Blvd Ste 300","cityState":"Georgetown TX 78628-3034","phone":"Phone: (918) 473-0285","fax":"Fax: ","webSite":"Website: "},{"name":"Adam Tyler Barnes, Dds Of Texas Ii, Pllc","street":"5695 Kyle Pkwy 250","cityState":"Kyle TX 78640-6305","phone":"Phone: (918) 473-0285","fax":"Fax: (918) 473-0346","webSite":"Website: "},{"name":"Adam Tyler Barnes, Dds Of Texas Ii, Pllc","street":"1704 Military Pkwy 700","cityState":"Mesquite TX 75149-3673","phone":"Phone: (972) 288-7272","fax":"Fax: ","webSite":"Website: "},{"name":"Adam Tyler Barnes, Dds Of Texas Ii, Pllc","street":"2317 W University Dr Ste B8 ","cityState":"Denton TX 76201-1699","phone":"Phone: (940) 566-0127","fax":"Fax: ","webSite":"Website: "},{"name":"Adam Tyler Barnes, Dds Of Texas Ii, Pllc","street":"9360 N Sam Houston Pkwy E Ste 800 ","cityState":"Humble TX 77396-5025","phone":"Phone: (281) 888-8750","fax":"Fax: ","webSite":"Website: "},{"name":"Adam Tyler Barnes, Dds Of Texas Ii, Pllc","street":"1151 E Hwy 377 Ste 101 ","cityState":"Granbury TX 76048-4009","phone":"Phone: (817) 578-3178","fax":"Fax: ","webSite":"Website: "},{"name":"Adam Tyler Barnes, Dds Of Texas Ii, Pllc","street":"6316 Azle Ave Suite 200","cityState":"Lake Worth TX 76135-2442","phone":"Phone: (817) 237-7377","fax":"Fax: ","webSite":"Website: "},{"name":"Adam Tyler Barnes, Dds Of Texas Ii, Pllc","street":"3103 I-30 Frontage Rd ","cityState":"Greenville TX 75402","phone":"Phone: (903) 201-8383","fax":"Fax: ","webSite":"Website: "},{"name":"Adam Tyler Barnes, Dds Of Texas Ii, Pllc","street":"12700 Lexington Street Suite 220","cityState":"Manor TX 78653","phone":"Phone: (512) 337-8399","fax":"Fax: ","webSite":"Website: "},{"name":"Adam Tyler Barnes, Dds Of Texas Ii, Pllc","street":"3916 Call Field Rd Ste 600","cityState":"Wichita Falls TX 76308-2693","phone":"Phone: (940) 217-6000","fax":"Fax: (918) 473-8100","webSite":"Website: "},{"name":"Adam Tyler Barnes, Dds Of Texas Ii, Pllc","street":"4522 Fredericksburg Rd #A-29","cityState":"San Antonio TX 78201-6521","phone":"Phone: (210) 660-8444","fax":"Fax: ","webSite":"Website: "},{"name":"Adam Tyler Barnes, Dds Of Texas Ii, Pllc","street":"8514 Highway 6 N ","cityState":"Houston TX 77095-2103","phone":"Phone: (281) 463-6422","fax":"Fax: ","webSite":"Website: "},{"name":"Adam Tyler Barnes, Dds Of Texas Ii, Pllc","street":"901 East Harwood Rd Suite 100","cityState":"Euless TX 76039","phone":"Phone: (817) 391-8991","fax":"Fax: ","webSite":"Website: "},{"name":"Adam Tyler Barnes, Dds Of Texas Ii, Pllc","street":"8938 South Broadway Ste 480","cityState":"Tyler TX 75703","phone":"Phone: (903) 201-8380","fax":"Fax: ","webSite":"Website: "},{"name":"Adam Tyler Barnes, Dds Of Texas Ii, Pllc","street":"5225 Belt Line Rd Ste 222 ","cityState":"Dallas TX 75254-1436","phone":"Phone: (972) 770-0055","fax":"Fax: ","webSite":"Website: "},{"name":"Adam Veitschegger Dds Pllc","street":"2105 Park Plaza Dr ","cityState":"Springfield TN 37172-3937","phone":"Phone: (615) 384-2558","fax":"Fax: (615) 384-2608","webSite":"Website: "},{"name":"Adam Weems D.M.D., P.A.","street":"1705 Strong Ave Suite A","cityState":"Greenwood MS 38930-3923","phone":"Phone: (662) 453-6243","fax":"Fax: ","webSite":"Website: "},{"name":"Amsterdam Oral Surgery & Dental Implant Center","street":"37 Prospect St ","cityState":"Amsterdam NY 12010-3614","phone":"Phone: (518) 514-3983","fax":"Fax: ","webSite":"Website: "},{"name":"Adam Yang Dds Ps","street":"15 Oregon Ave Ste 106 ","cityState":"Tacoma WA 98409-7462","phone":"Phone: (253) 475-0262","fax":"Fax: (253) 475-0266","webSite":"Website: "},{"name":"Adam Yang Dds Ps","street":"8811 S Tacoma Way Ste 103 ","cityState":"Lakewood WA 98499-4595","phone":"Phone: (253) 983-9090","fax":"Fax: (253) 983-1225","webSite":"Website: "},{"name":"Adam, Amman","street":"6060 I Mcdonough Dr. ","cityState":"Norcross GA 30093","phone":"Phone: (770) 448-3020","fax":"Fax: (770) 447-4106","webSite":"Website: "},{"name":"Adam, Andrea","street":"40W320 Lafox Rd Suite D","cityState":"St Charles IL 60175-6545","phone":"Phone: (630) 762-0000","fax":"Fax: (630) 762-9966","webSite":"Website: "},{"name":"Adam, Anne M.","street":"102 North Pike Rd. ","cityState":"Sarver PA 16055-9254","phone":"Phone: (724) 353-1521","fax":"Fax: (724) 295-3749","webSite":"Website: "},{"name":"Adam, Ashraf Yasien","street":"6316 Castle Pl Ste 201 ","cityState":"Falls Church VA 22044-1906","phone":"Phone: (703) 237-7777","fax":"Fax: (703) 533-2036","webSite":"Website: "},{"name":"Adam, Elizabeth","street":"102 N. Pike Rd ","cityState":"Sarver PA 16055","phone":"Phone: (724) 353-1521","fax":"Fax: (724) 295-3749","webSite":"Website: "},{"name":"Adam, Emilia C","street":"13831 Nw Cornell Rd C","cityState":"Portland OR 97229-5485","phone":"Phone: (503) 718-3762","fax":"Fax: (503) 718-3766","webSite":"Website: "},{"name":"Adam, Gehan","street":"447 Fulton St ","cityState":"Brooklyn NY 11201-5207","phone":"Phone: (718) 875-3200","fax":"Fax: (718) 875-4573","webSite":"Website: "},{"name":"Adam, John Michael","street":"1311 S Miller St #201","cityState":"Santa Maria CA 93454","phone":"Phone: (805) 928-2597","fax":"Fax: (805) 928-0789","webSite":"Website: "},{"name":"Adam, Laura","street":"2335 Hwy 92 E ","cityState":"Oskaloosa IA 52577","phone":"Phone: (641) 673-8455","fax":"Fax: ","webSite":"Website: "},{"name":"Adam, Lawrence G.","street":"102 North Pike Rd ","cityState":"Sarver PA 16055","phone":"Phone: (724) 353-1521","fax":"Fax: (724) 295-3749","webSite":"Website: "},{"name":"Adam, Lawrence Joseph","street":"102 N. Pike Rd. ","cityState":"Sarver PA 16055","phone":"Phone: (724) 353-1521","fax":"Fax: (724) 295-3749","webSite":"Website: "},{"name":"Adam, Mark S","street":"125 E Stowell Rd #103 ","cityState":"Santa Maria CA 93454","phone":"Phone: (805) 928-4391","fax":"Fax: (805) 925-4166","webSite":"Website: "},{"name":"Adam, Shawna","street":"Uss Mesa Verde (Lpd 19) ","cityState":"Fpo AE 09578-1702","phone":"Phone: (979) 218-5994","fax":"Fax: ","webSite":"Website: "},{"name":"Adam, Sophie Rejeanne","street":"1106 W River Rd ","cityState":"Detroit Lakes MN 56501-2723","phone":"Phone: (218) 846-1900","fax":"Fax: ","webSite":"Website: "},{"name":"Adam, Stephen M","street":"3272 E Rio Virgin Rd ","cityState":"Littlefield AZ 86432-3200","phone":"Phone: (435) 668-4057","fax":"Fax: ","webSite":"Website: "},{"name":"Adam, Stuart Stephen","street":"125 E Stowell Rd Ste 103 ","cityState":"Santa Maria CA 93454-6681","phone":"Phone: (805) 928-4391","fax":"Fax: ","webSite":"Website: "},{"name":"Adamchuk, Timothy R","street":"275 W Kaahumanu Ave ","cityState":"Kahului HI 96732-1629","phone":"Phone: (808) 856-4640","fax":"Fax: ","webSite":"Website: "},{"name":"Adamcik, Ashlyn Nicole","street":"6704 Sterling Ridge Dr Ste G ","cityState":"The Woodlands TX 77382-2329","phone":"Phone: (281) 298-0999","fax":"Fax: ","webSite":"Website: "},{"name":"Adamczak, James A","street":"210 3Rd St ","cityState":"Carlton MN 55718-7703","phone":"Phone: (218) 336-3524","fax":"Fax: (218) 384-9002","webSite":"Website: "},{"name":"Adamczuk, Ophelia Garcia-","street":"8992 Mission Blvd Ste A","cityState":"Riverside CA 92509-2874","phone":"Phone: (951) 681-6611","fax":"Fax: (951) 681-6611","webSite":"Website: "},{"name":"Adamczyk, Raymond Joseph","street":"834 E Rand Road Unit 3","cityState":"Mount Prospect IL 60056-2569","phone":"Phone: (847) 368-0868","fax":"Fax: (847) 368-0868","webSite":"Website: "},{"name":"Adamczyk, Theresa","street":"2310 Westowne Ave ","cityState":"Oshkosh WI 54904-7778","phone":"Phone: (920) 731-7445","fax":"Fax: (920) 651-3485","webSite":"Website: "},{"name":"Adame & Adame, D.D.S.","street":"2155 North Arrowhead Avenue ","cityState":"San Bernardino CA 92405-4001","phone":"Phone: (909) 886-1144","fax":"Fax: (909) 886-8726","webSite":"Website: "},{"name":"Adame Dental Sleep Medicine, Pllc","street":"206 W Mahl St ","cityState":"Edinburg TX 78539-4331","phone":"Phone: (956) 867-1585","fax":"Fax: ","webSite":"Website: "},{"name":"Adame Dental Sleep Medicine, Pllc","street":"5300 N Mccoll Rd Ste 100 ","cityState":"Mcallen TX 78504","phone":"Phone: (956) 994-9988","fax":"Fax: ","webSite":"Website: "},{"name":"Adame Villarreal, Christina","street":"501 E Princeton Dr Suite 103B","cityState":"Princeton TX 75407-9010","phone":"Phone: (972) 736-3888","fax":"Fax: ","webSite":"Website: "},{"name":"Adame, David Filippini","street":"1811 North Waterman Avenue ","cityState":"San Bernardino CA 92404","phone":"Phone: (909) 886-3211","fax":"Fax: (909) 882-8521","webSite":"Website: "},{"name":"Adame, David Omar","street":"210 W Mahl St ","cityState":"Edinburg TX 78539-4331","phone":"Phone: (956) 381-8262","fax":"Fax: (956) 381-9193","webSite":"Website: "},{"name":"Adame, James Filippini","street":"2155 North Arrowhead Avenue ","cityState":"San Bernardino CA 92405-4001","phone":"Phone: (909) 886-1144","fax":"Fax: (909) 886-8726","webSite":"Website: "},{"name":"Adame, Joseph Michael","street":"206 W Mahl ","cityState":"Edinburg TX 78539","phone":"Phone: (956) 383-4400","fax":"Fax: (956) 383-6005","webSite":"Website: "},{"name":"Adame, Samuel Filippini","street":"2155 North Arrowhead Avenue ","cityState":"San Bernardino CA 92405-4001","phone":"Phone: (909) 886-1144","fax":"Fax: (909) 886-8726","webSite":"Website: "},{"name":"Adame, Steven","street":"773B 14Th St ","cityState":"San Francisco CA 94114-1322","phone":"Phone: (415) 626-0480","fax":"Fax: (415) 626-0492","webSite":"Website: "},{"name":"Adame, Thomas C","street":"1653 Solano Ave ","cityState":"Berkeley CA 94707-2108","phone":"Phone: (510) 524-1172","fax":"Fax: ","webSite":"Website: "},{"name":"Adamec, Deborah Kay","street":"300 Dental Science N ","cityState":"Iowa City IA 52242-1010","phone":"Phone: (319) 335-7447","fax":"Fax: ","webSite":"Website: "},{"name":"Adamek, Dustin Jacob","street":"6830 E Sam Houston Pkwy N Suite 100","cityState":"Houston TX 77049-7301","phone":"Phone: (713) 451-8845","fax":"Fax: ","webSite":"Website: "},{"name":"Adames Ramirez, Mary Isabel","street":"527 Ne 124Th St ","cityState":"North Miami FL 33161-5423","phone":"Phone: (305) 895-6590","fax":"Fax: (305) 895-9274","webSite":"Website: "},{"name":"Adames, Angelina M","street":"111 E 210Th St ","cityState":"Bronx NY 10467","phone":"Phone: (718) 920-4321","fax":"Fax: ","webSite":"Website: "},{"name":"Adames, Renata B","street":"570 W 19Th St ","cityState":"Costa Mesa CA 92627","phone":"Phone: (949) 642-4222","fax":"Fax: (949) 642-4657","webSite":"Website: "},{"name":"Adametz, Joshua Ross","street":"2719 Calumet Ave ","cityState":"Manitowoc WI 54220-5546","phone":"Phone: (920) 686-2333","fax":"Fax: ","webSite":"Website: "},{"name":"Adami, Diba","street":"522 S San Pedro St ","cityState":"Los Angeles CA 90013-2102","phone":"Phone: (213) 486-4045","fax":"Fax: ","webSite":"Website: "},{"name":"Adami, Dina","street":"30406 Haun Rd 740","cityState":"Menifee CA 92584-6816","phone":"Phone: (951) 679-4624","fax":"Fax: ","webSite":"Website: "},{"name":"Adami, Marjan","street":"2200 Woodland Oaks Dr ","cityState":"Arlington TX 76013-5319","phone":"Phone: (405) 570-3043","fax":"Fax: ","webSite":"Website: "},{"name":"Adami, Meena","street":"107 Jennifer St ","cityState":"Redlands CA 92373-4957","phone":"Phone: (501) 766-6479","fax":"Fax: ","webSite":"Website: "},{"name":"Adami, Mustafa","street":"2094 E Highland Ave ","cityState":"San Bernardino CA 92404-4626","phone":"Phone: (909) 388-2427","fax":"Fax: ","webSite":"Website: "},{"name":"Adami, Robert Alfred","street":"16235 Sr7 ","cityState":"Delray Beach FL 33446","phone":"Phone: (561) 637-4443","fax":"Fax: (561) 637-4428","webSite":"Website: "},{"name":"Adamiak, Brittany S","street":"131 Indian Lake Rd Suite 101","cityState":"Hendersonville TN 37075-3866","phone":"Phone: (615) 824-1700","fax":"Fax: (615) 826-2266","webSite":"Website: "},{"name":"Marek Adamiak                                                                        ","street":"7106 Moores Ln Brentwood, TN 37027-2903"},{"name":"Adamian, Evlin","street":"1125 Tremont St ","cityState":"Roxbury Crossing MA 02120-2178","phone":"Phone: (617) 989-3240","fax":"Fax: ","webSite":"Website: "},{"name":"Adamian, Joseph","street":"206 N Jackson St Suite 302","cityState":"Glendale CA 91206-4330","phone":"Phone: (818) 500-1735","fax":"Fax: (818) 500-0434","webSite":"Website: "},{"name":"Adamian, Melina","street":"241 E Elmwood Ave Apt 211 ","cityState":"Burbank CA 91502-2665","phone":"Phone: (818) 281-1710","fax":"Fax: ","webSite":"Website: "},{"name":"Adamian, Sevak","street":"1275 Ne Franklin Ave ","cityState":"Bremerton WA 98311-3005","phone":"Phone: (360) 377-3779","fax":"Fax: ","webSite":"Website: "},{"name":"Adamic, David Duane","street":"810 St John Place Suite A","cityState":"Hemet CA 92543-4414","phone":"Phone: (951) 652-6767","fax":"Fax: (951) 652-9612","webSite":"Website: "},{"name":"Adamich, Thomas Steven","street":"18821 Delaware St Suite 201","cityState":"Huntington Beach CA 92648-1936","phone":"Phone: (714) 842-6631","fax":"Fax: (714) 848-8568","webSite":"Website: "},{"name":"Adamidis, Theodore J","street":"365 Willard Ave ","cityState":"Newington CT 06111-2373","phone":"Phone: (860) 666-7910","fax":"Fax: ","webSite":"Website: "},{"name":"Adamjee, Ashi Hafeez","street":"169 Park Ave ","cityState":"Yonkers NY 10703-2907","phone":"Phone: (914) 965-4233","fax":"Fax: ","webSite":"Website: "},{"name":"Adamo, Anthony D","street":"24700 Center Ridge Rd. 316","cityState":"Westlake OH 44145","phone":"Phone: (440) 835-3331","fax":"Fax: ","webSite":"Website: "},{"name":"Adamo, Arthur","street":"1400 Pelham Pkwy S ","cityState":"Bronx NY 10461-1138","phone":"Phone: (718) 918-3060","fax":"Fax: (718) 918-4469","webSite":"Website: "},{"name":"Adamo, Charles Thomas","street":"8418 Old Mcgregor Rd ","cityState":"Waco TX 76712-6494","phone":"Phone: (254) 754-1456","fax":"Fax: (254) 754-0907","webSite":"Website: "},{"name":"Adamo, Daniele","street":"2261 Randall Rd ","cityState":"Carpentersville IL 60110-3355","phone":"Phone: (224) 484-8221","fax":"Fax: ","webSite":"Website: "},{"name":"Adamo, James E","street":"16829 S Water Tower Dr Unit 5","cityState":"Kincheloe MI 49788-1500","phone":"Phone: (906) 495-5525","fax":"Fax: (906) 495-1411","webSite":"Website: "},{"name":"Adamo, John Battista","street":"31625 Highway 101 S ","cityState":"Soledad CA 93960-9529","phone":"Phone: (831) 678-5595","fax":"Fax: (831) 678-6273","webSite":"Website: "},{"name":"Adamonis, Adam Wincenty","street":"1720 2Nd St ","cityState":"Cheney WA 99004-1910","phone":"Phone: (509) 444-8200","fax":"Fax: ","webSite":"Website: "},{"name":"Adamos, Aldrin Abad","street":"219 Division St ","cityState":"Pleasanton CA 94566-6609","phone":"Phone: (925) 846-2228","fax":"Fax: (925) 846-1670","webSite":"Website: "},{"name":"Adamous, Hooman","street":"14343 Bellflower Blvd ","cityState":"Bellflower CA 90706-3135","phone":"Phone: (562) 866-1111","fax":"Fax: (562) 866-1130","webSite":"Website: "},{"name":"Adamov, Ivana","street":"111 Willard St Suite 1B","cityState":"Quincy MA 02169-1200","phone":"Phone: (617) 471-8640","fax":"Fax: ","webSite":"Website: "},{"name":"Adams & Seaton Pediatric Dentistry","street":"5115 Harding Pike Ste 201 ","cityState":"Nashville TN 37205-2722","phone":"Phone: (615) 297-7597","fax":"Fax: (615) 269-7132","webSite":"Website: "},{"name":"Brookland Dental","street":"8377 Hwy 49 N ","cityState":"Brookland AR 72417-8006","phone":"Phone: (870) 933-1900","fax":"Fax: (870) 933-8383","webSite":"Website: "},{"name":"Adams & Toney Dds Pllc","street":"8377 Hwy 49 N ","cityState":"Brookland AR 72417-8006","phone":"Phone: (870) 393-5330","fax":"Fax: (870) 393-5331","webSite":"Website: "},{"name":"Dentistry For Children","street":"300 W Broad St ","cityState":"Richmond VA 23220-4219","phone":"Phone: (804) 780-2888","fax":"Fax: (804) 643-1916","webSite":"Website: "},{"name":"Adams And Cheek Dentistry","street":"11001 Raven Ridge Rd Suite 101","cityState":"Raleigh NC 27614-6687","phone":"Phone: (919) 866-1360","fax":"Fax: (919) 866-1365","webSite":"Website: "},{"name":"Adams Arch Dental Llc","street":"241 W Forest St ","cityState":"Brigham City UT 84302-2022","phone":"Phone: (435) 723-6120","fax":"Fax: ","webSite":"Website: "},{"name":"Adams Browne Dental Associates","street":"1128 Winchester Rd Ste 108 ","cityState":"Memphis TN 38116-3151","phone":"Phone: (901) 332-7111","fax":"Fax: (901) 332-7733","webSite":"Website: "},{"name":"Adams Dental","street":"801 Adams Ave ","cityState":"Philadelphia PA 19124-2327","phone":"Phone: (215) 744-8300","fax":"Fax: (215) 744-7840","webSite":"Website: "},{"name":"Adams Dental Group","street":"2119 Minnesota Ave ","cityState":"Kansas City KS 66102-4145","phone":"Phone: (913) 621-3113","fax":"Fax: ","webSite":"Website: "},{"name":"Adams Dental Llc","street":"1 Kings Rd ","cityState":"Madison NJ 07940-2016","phone":"Phone: (973) 377-6500","fax":"Fax: ","webSite":"Website: "},{"name":"Adams Dental Pplc","street":"111 S Public Sq ","cityState":"Alexandria TN 37012-2140","phone":"Phone: (615) 529-2895","fax":"Fax: (615) 529-2738","webSite":"Website: "},{"name":"Adams Family And Cosmetic Dentistry","street":"5605 Princeton Ave Suite B","cityState":"Columbus GA 31904-9078","phone":"Phone: (706) 323-8811","fax":"Fax: (706) 323-8824","webSite":"Website: "},{"name":"Adams Family Dental","street":"5600 W 87Th St ","cityState":"Burbank IL 60459-2902","phone":"Phone: (708) 952-0000","fax":"Fax: (708) 952-0001","webSite":"Website: "},{"name":"Adams Iii, Robert Arman","street":"1407 South Rd ","cityState":"Morgan City LA 70380-5607","phone":"Phone: (985) 395-2436","fax":"Fax: (985) 395-2491","webSite":"Website: "},{"name":"Adams Oral Surgery Inc","street":"455 South Washington St #21 ","cityState":"Gettysburg PA 17325","phone":"Phone: (717) 337-3232","fax":"Fax: (717) 337-1032","webSite":"Website: "},{"name":"Adams Oral Surgery Inc","street":"249 Allejheny Ave ","cityState":"Hanover PA 17331","phone":"Phone: (717) 637-5196","fax":"Fax: (717) 637-5085","webSite":"Website: "},{"name":"Adams Shaffer Dds Inc","street":"3694 Hilborn Rd Ste 100 ","cityState":"Fairfield CA 94534-7994","phone":"Phone: (707) 422-5444","fax":"Fax: (707) 422-1613","webSite":"Website: "},{"name":"Adams Smile Center","street":"46161 Westlake Dr Ste 220 ","cityState":"Sterling VA 20165-5871","phone":"Phone: (703) 430-1212","fax":"Fax: (703) 430-2373","webSite":"Website: "},{"name":"Adams Smile Center Pllc","street":"46161 Westlake Dr Suite 220","cityState":"Sterling VA 20165-5871","phone":"Phone: (703) 430-1212","fax":"Fax: ","webSite":"Website: "},{"name":"Adams&Gimlen Dental Partnership","street":"973 Manhattan Beach Blvd #C","cityState":"Manhattan Beach CA 90266-5131","phone":"Phone: (310) 545-6525","fax":"Fax: (310) 546-6203","webSite":"Website: "},{"name":"Adams, A Paul","street":"311 E 500 S ","cityState":"Bountiful UT 84010-4924","phone":"Phone: (801) 295-5796","fax":"Fax: (801) 295-7516","webSite":"Website: "},{"name":"Adams, Abigail Northcutt","street":"4519 Woodruff Rd #10","cityState":"Columbus GA 31904-6011","phone":"Phone: (706) 405-3772","fax":"Fax: ","webSite":"Website: "},{"name":"Adams, Adams, And Epperly Dds Pc","street":"4315 Grove Avenue ","cityState":"Richmond VA 23221","phone":"Phone: (804) 285-1378","fax":"Fax: (804) 285-1388","webSite":"Website: "},{"name":"Adams, Alec Alexander","street":"1663 Glenns Bay Rd ","cityState":"Myrtle Beach SC 29575-4836","phone":"Phone: (843) 215-6080","fax":"Fax: ","webSite":"Website: "},{"name":"Adams, Allison Mercy","street":"1 Kings Road ","cityState":"Madison NJ 07940-2338","phone":"Phone: (973) 377-6500","fax":"Fax: (973) 695-2050","webSite":"Website: "},{"name":"Adams, Allysa Claire","street":"103 Fite Way Suite A","cityState":"Quarryville PA 17566-9394","phone":"Phone: (717) 786-1717","fax":"Fax: (717) 786-8508","webSite":"Website: "},{"name":"Adams, Amanda Lanell","street":"46 Post Oak Trl ","cityState":"Inez TX 77968-4044","phone":"Phone: (979) 551-5484","fax":"Fax: ","webSite":"Website: "},{"name":"Adams, Andrew Ayres","street":"512 Reed Road ","cityState":"Anderson SC 29621","phone":"Phone: (864) 226-6278","fax":"Fax: ","webSite":"Website: "},{"name":"Adams, Andrew Jason","street":"58 Old North Rd ","cityState":"Worthington MA 01098-9753","phone":"Phone: (413) 238-5511","fax":"Fax: ","webSite":"Website: "},{"name":"Adams, Anna Margaret","street":"10207 Cerny St Ste 106 ","cityState":"Raleigh NC 27617-4880","phone":"Phone: (919) 336-2981","fax":"Fax: ","webSite":"Website: "},{"name":"Adams, Anne Carter","street":"10127 West Broad Street Suite Q","cityState":"Glen Allen VA 23060","phone":"Phone: (804) 270-6808","fax":"Fax: (804) 270-1963","webSite":"Website: "},{"name":"Adams, Anthony","street":"20285 Sw Tualatin Valley Hwy ","cityState":"Aloha OR 97003","phone":"Phone: (360) 870-9899","fax":"Fax: ","webSite":"Website: "},{"name":"Adams, Anthony Joe","street":"25877 Us Highway 19 N ","cityState":"Clearwater FL 33763","phone":"Phone: (727) 799-3123","fax":"Fax: (727) 799-2740","webSite":"Website: "},{"name":"Adams, Arthur","street":"534 Shelton Ave ","cityState":"Shelton CT 06484-2804","phone":"Phone: (203) 929-6338","fax":"Fax: ","webSite":"Website: "},{"name":"Adams, Asja M","street":"4202 198Th St Sw ","cityState":"Lynnwood WA 98036-6730","phone":"Phone: (425) 775-0651","fax":"Fax: (425) 771-5085","webSite":"Website: "},{"name":"Adams, Benjamin George","street":"809 State Rd. 44 ","cityState":"New Smyrna Beach FL 32168","phone":"Phone: (386) 428-6491","fax":"Fax: ","webSite":"Website: "},{"name":"Adams, Benjamin H","street":"3750 Guion Rd #280","cityState":"Indianapolis IN 46222-7602","phone":"Phone: (317) 924-3228","fax":"Fax: (317) 924-3737","webSite":"Website: "},{"name":"Adams, Benjamin Stanford","street":"870 Cleveland St Suite 1-A","cityState":"Greenville SC 29601-4427","phone":"Phone: (864) 233-0427","fax":"Fax: (864) 271-2295","webSite":"Website: "},{"name":"Adams, Bianca Kristina","street":"207 Forest Creek Dr ","cityState":"Fayetteville NC 28303-5496","phone":"Phone: (770) 617-4412","fax":"Fax: ","webSite":"Website: "},{"name":"Adams, Billie Elizabeth","street":"10429 Montgomery Pkwy Ne ","cityState":"Albuquerque NM 87111-3864","phone":"Phone: (505) 293-2211","fax":"Fax: (505) 293-0915","webSite":"Website: "},{"name":"Adams, Blaine Paul","street":"707 Crescent Ave ","cityState":"Lockport LA 70374-2815","phone":"Phone: (985) 532-3480","fax":"Fax: ","webSite":"Website: "},{"name":"Adams, Blake","street":"1647 Admiral Taussig Blvd ","cityState":"Norfolk VA 23511-2803","phone":"Phone: (757) 953-8591","fax":"Fax: ","webSite":"Website: "},{"name":"Adams, Blake Ryan","street":"3401 Nw 23Rd St ","cityState":"Oklahoma City OK 73107-1803","phone":"Phone: (405) 949-0123","fax":"Fax: ","webSite":"Website: "},{"name":"Adams, Bradley","street":"1428 Main St ","cityState":"Walpole MA 02081-1729","phone":"Phone: (508) 668-8008","fax":"Fax: ","webSite":"Website: "},{"name":"Adams, Bradley Aaron","street":"3310 Mesa Way ","cityState":"Lawrence KS 66049-2361","phone":"Phone: (785) 843-2636","fax":"Fax: ","webSite":"Website: "},{"name":"Adams, Bradley Olin","street":"101 W Northside Dr Bldg B","cityState":"Valdosta GA 31602-1714","phone":"Phone: (229) 247-6960","fax":"Fax: (229) 247-8870","webSite":"Website: "},{"name":"Adams, Brandy Nichole","street":"500 Southland Dr Ste 150 ","cityState":"Birmingham AL 35226-3726","phone":"Phone: (205) 823-1136","fax":"Fax: (205) 823-8826","webSite":"Website: "},{"name":"Adams, Brannick Don","street":"1539 W Harvard Ave ","cityState":"Roseburg OR 97470-2873","phone":"Phone: (541) 673-5150","fax":"Fax: ","webSite":"Website: "},{"name":"Adams, Brian J","street":"280 Vista Knoll Pkwy Ste 114 ","cityState":"Reno NV 89506-5649","phone":"Phone: (775) 384-0074","fax":"Fax: ","webSite":"Website: "},{"name":"Adams, Brian Russell","street":"301 Sycamore Valley Rd West ","cityState":"Danville CA 94526","phone":"Phone: (925) 820-6466","fax":"Fax: (925) 820-6606","webSite":"Website: "},{"name":"Adams, Brian Scott","street":"1448 Bridgegate Dr ","cityState":"Diamond Bar CA 91765-3922","phone":"Phone: (909) 860-4300","fax":"Fax: ","webSite":"Website: "},{"name":"Adams, Brooke N","street":"1121 W Michigan Street Ds307B","cityState":"Indianapolis IN 46202-5186","phone":"Phone: (615) 373-8001","fax":"Fax: (615) 371-9589","webSite":"Website: "},{"name":"Adams, Bruce R","street":"2828 Grand Avenue ","cityState":"Laramie WY 82070","phone":"Phone: (307) 721-2900","fax":"Fax: (307) 742-0002","webSite":"Website: "},{"name":"Adams, Bruce William","street":"555 S Rancho Santa Fe Rd Suite 204","cityState":"San Marcos CA 92078-3698","phone":"Phone: (760) 471-6801","fax":"Fax: (760) 471-9080","webSite":"Website: "},{"name":"Adams, Bryan","street":"1600 Sw Archer Rd # D7-6 Box 100416","cityState":"Gainesville FL 32610-3003","phone":"Phone: (352) 273-6750","fax":"Fax: (352) 392-7609","webSite":"Website: "},{"name":"Adams, Cally Lane","street":"7 Waterfront Pl 500 Ala Moana Blvd Suite 220","cityState":"Honolulu HI 96813-4920","phone":"Phone: (808) 523-3103","fax":"Fax: (808) 523-3122","webSite":"Website: "},{"name":"Adams, Carlton Bradley","street":"206 W Ash St ","cityState":"Goldsboro NC 27530-3663","phone":"Phone: (919) 734-6386","fax":"Fax: (919) 734-6387","webSite":"Website: "},{"name":"Adams, Caroline Michelle","street":"18 Hillside Dr ","cityState":"Holliston MA 01746-1480","phone":"Phone: (774) 217-4298","fax":"Fax: ","webSite":"Website: "},{"name":"Adams, Cary A","street":"Old Orchard Prof. Bldg. 64 Old Orchard Road, Su. 500","cityState":"Skokie IL 60077","phone":"Phone: (847) 677-8553","fax":"Fax: ","webSite":"Website: "},{"name":"Adams, Cary M.","street":"821 University Blvd S ","cityState":"Mobile AL 36609-7873","phone":"Phone: (251) 343-3214","fax":"Fax: (251) 343-3207","webSite":"Website: "},{"name":"Adams, Charles Gregory","street":"185 Pat Haralson Memorial Dr ","cityState":"Blairsville GA 30512-3008","phone":"Phone: (706) 835-2400","fax":"Fax: (706) 835-2500","webSite":"Website: "},{"name":"Adams, Chester Trent","street":"51 S White Mountain Rd ","cityState":"Show Low AZ 85901-6105","phone":"Phone: (928) 537-2525","fax":"Fax: (928) 537-2525","webSite":"Website: "},{"name":"Adams, Chester Trent","street":"51 S White Mountain Rd ","cityState":"Show Low AZ 85901-6105","phone":"Phone: (928) 537-1282","fax":"Fax: ","webSite":"Website: "},{"name":"Adams, Chloe Mai","street":"1789 Nw 173Rd Ave ","cityState":"Beaverton OR 97006","phone":"Phone: (714) 204-8508","fax":"Fax: ","webSite":"Website: "},{"name":"Adams, Christine","street":"900 Nw 13Th St Ste 101 ","cityState":"Boca Raton FL 33486-2350","phone":"Phone: (561) 395-3284","fax":"Fax: ","webSite":"Website: "},{"name":"Adams, Christopher Barton","street":"1685 Mars Hill Road Nw Bldg 200 Ste 200","cityState":"Acworth GA 30101","phone":"Phone: (770) 919-0930","fax":"Fax: (770) 919-2309","webSite":"Website: "},{"name":"Adams, Christopher Kirk","street":"1683 W Harvard Ave ","cityState":"Roseburg OR 97471-2812","phone":"Phone: (541) 673-3552","fax":"Fax: ","webSite":"Website: "},{"name":"Adams, Clement V","street":"3081 Oak Valley Dr ","cityState":"Ann Arbor MI 48103","phone":"Phone: (734) 213-6200","fax":"Fax: (734) 213-6900","webSite":"Website: "},{"name":"Adams, Courtney","street":"4315 Grove Avenue ","cityState":"Richmond VA 23221","phone":"Phone: (804) 285-1378","fax":"Fax: (804) 285-1388","webSite":"Website: "},{"name":"Adams, Craig D","street":"107 N Greenfield Rd Suite 1","cityState":"Mesa AZ 85205-7802","phone":"Phone: (480) 832-5900","fax":"Fax: ","webSite":"Website: "},{"name":"Adams, Craig Q","street":"11001 Raven Ridge Rd Suite 101","cityState":"Raleigh NC 27614-6687","phone":"Phone: (919) 866-1360","fax":"Fax: (919) 866-1365","webSite":"Website: "},{"name":"Adams, Curtis Wendel","street":"9 E Main Street ","cityState":"Flemington NJ 08822","phone":"Phone: (908) 782-3040","fax":"Fax: (908) 782-7351","webSite":"Website: "},{"name":"Adams, Cynthia Kay","street":"1010 Delafield Rd Va Medical Center","cityState":"Pittsburgh PA 15240-1005","phone":"Phone: (412) 784-3554","fax":"Fax: (412) 784-3841","webSite":"Website: "},{"name":"Adams, Dana Louise","street":"9735 Wilshire Blvd Ste 432","cityState":"Beverly Hills CA 90212","phone":"Phone: (310) 276-0746","fax":"Fax: (310) 276-8414","webSite":"Website: "},{"name":"Adams, Daniel Robert","street":"6965 El Camino Real Ste 201 ","cityState":"Carlsbad CA 92009-4102","phone":"Phone: (760) 804-0080","fax":"Fax: ","webSite":"Website: "},{"name":"Adams, Danny Lawrence","street":"202 S King St ","cityState":"Leesburg VA 20175-3010","phone":"Phone: (703) 777-1162","fax":"Fax: (703) 779-2149","webSite":"Website: "},{"name":"Adams, David","street":"108 N Main St ","cityState":"Lawrenceburg KY 40342-1014","phone":"Phone: (502) 839-3485","fax":"Fax: ","webSite":"Website: "},{"name":"Adams, David C","street":"420 Spruce St Suite B","cityState":"San Diego CA 92103-5800","phone":"Phone: (619) 291-5266","fax":"Fax: (619) 291-0124","webSite":"Website: "},{"name":"Adams, David Isaac","street":"7204 267Th St Nw #102","cityState":"Stanwood WA 98292-6271","phone":"Phone: (360) 629-7229","fax":"Fax: ","webSite":"Website: "},{"name":"Adams, David Jonathan","street":"925 Heather Park Drive ","cityState":"Garner NC 27529","phone":"Phone: (919) 772-0314","fax":"Fax: (919) 772-2606","webSite":"Website: "},{"name":"Adams, David Michael","street":"595 N Center Rd ","cityState":"Saginaw MI 48638-5871","phone":"Phone: (989) 799-1410","fax":"Fax: (989) 799-1438","webSite":"Website: "},{"name":"Adams, David Roger","street":"11 Birdsall St ","cityState":"Norwich NY 13815-1812","phone":"Phone: (607) 334-8038","fax":"Fax: ","webSite":"Website: "},{"name":"David Russell Adams                                                                        ","street":"1111 E Herndon Ave Ste 119 Fresno, CA 93720-3100"},{"name":"Adams, David V","street":"821 S University Blvd ","cityState":"Mobile AL 36609-7873","phone":"Phone: (251) 343-3214","fax":"Fax: (251) 343-3207","webSite":"Website: "},{"name":"Adams, Dawne Elizabeth","street":"3427 Norwood St ","cityState":"Ann Arbor MI 48104-5345","phone":"Phone: (734) 649-4453","fax":"Fax: ","webSite":"Website: "},{"name":"Adams, Deborah S.","street":"329 E Main St Suite 7","cityState":"Smithtown NY 11787-2830","phone":"Phone: (631) 265-9616","fax":"Fax: ","webSite":"Website: "},{"name":"Adams, Debra Gandy","street":"2053 Arundel Pl ","cityState":"Mt Pleasant SC 29464-6201","phone":"Phone: (843) 225-3353","fax":"Fax: ","webSite":"Website: "},{"name":"Adams, Delos Charles","street":"3915 Ogden Ave ","cityState":"Ogden UT 84403-1823","phone":"Phone: (801) 392-1000","fax":"Fax: (801) 393-4578","webSite":"Website: "},{"name":"Adams, Donald P.","street":"201 E Matthews Street ","cityState":"Matthews NC 28105","phone":"Phone: (704) 847-3355","fax":"Fax: (704) 847-3247","webSite":"Website: "},{"name":"Adams, Douglas Ray","street":"990 S Medical Drive ","cityState":"Brigham City UT 84302","phone":"Phone: (435) 723-6113","fax":"Fax: (435) 723-6113","webSite":"Website: "},{"name":"Adams, Elizabeth","street":"1075 Central Park Ave Suite 310","cityState":"Scarsdale NY 10583-3242","phone":"Phone: (914) 722-0511","fax":"Fax: (914) 722-0512","webSite":"Website: "},{"name":"Adams, Eric Paul","street":"1915 Valley Park Dr ","cityState":"Cedar Falls IA 50613-4443","phone":"Phone: (319) 277-1454","fax":"Fax: (319) 277-1458","webSite":"Website: "},{"name":"Adams, Evan Christopher","street":"909 Dairy Ashford Rd Ste 104 ","cityState":"Houston TX 77079","phone":"Phone: (281) 493-4173","fax":"Fax: (281) 493-4388","webSite":"Website: "},{"name":"Adams, Francis Wates","street":"303 W Alexander Ave Suite D-1","cityState":"Greenwood SC 29646-4078","phone":"Phone: (864) 229-5885","fax":"Fax: (864) 229-1002","webSite":"Website: "},{"name":"Adams, Gail Brent","street":"815 N 6Th E ","cityState":"Mountain Home ID 83647-2207","phone":"Phone: (208) 587-7949","fax":"Fax: (208) 587-2978","webSite":"Website: "},{"name":"Adams, Gary Deane","street":"6001 Montrose Rd Suite 1010","cityState":"Rockville MD 20852-4817","phone":"Phone: (301) 468-6200","fax":"Fax: (301) 468-5553","webSite":"Website: "},{"name":"Adams, George Austin","street":"4515 Harding Rd Suite 114","cityState":"Nashville TN 37205-2118","phone":"Phone: (615) 297-7597","fax":"Fax: (615) 269-7132","webSite":"Website: "},{"name":"Adams, George Austin","street":"4515 Harding Rd Suite 114","cityState":"Nashville TN 37205-2118","phone":"Phone: (615) 297-7597","fax":"Fax: (615) 269-7132","webSite":"Website: "},{"name":"Adams, George Quinlan","street":"2845 Parkwood Blvd. #100 ","cityState":"Plano TX 75093","phone":"Phone: (972) 867-7207","fax":"Fax: (972) 612-1471","webSite":"Website: "},{"name":"Adams, Gerald G.","street":"5605 Princeton Ave Suite B","cityState":"Columbus GA 31904-9078","phone":"Phone: (706) 323-8811","fax":"Fax: (706) 323-8824","webSite":"Website: "},{"name":"Adams, Greg Stanley","street":"1083 State Ave ","cityState":"Marysville WA 98270-4240","phone":"Phone: (360) 659-0864","fax":"Fax: (360) 651-1780","webSite":"Website: "},{"name":"Adams, Gregory L","street":"1100 Walnut St ","cityState":"Owensboro KY 42301-2956","phone":"Phone: (270) 684-2212","fax":"Fax: (270) 684-0068","webSite":"Website: "},{"name":"Adams, Gregory Lee","street":"7915 Laguna Blvd Ste 160 ","cityState":"Elk Grove CA 95758-7944","phone":"Phone: (916) 684-4886","fax":"Fax: (916) 684-1518","webSite":"Website: "},{"name":"Adams, Hans","street":"9871 S Parker Rd Suite 105","cityState":"Parker CO 80134-8802","phone":"Phone: (303) 805-5703","fax":"Fax: ","webSite":"Website: "},{"name":"Adams, Heather R","street":"613 3Rd Ave ","cityState":"Chula Vista CA 91910-5703","phone":"Phone: (619) 425-7700","fax":"Fax: (619) 425-5871","webSite":"Website: "},{"name":"Adams, Heather V","street":"4805 W Highland Knolls Rd Ste 300 ","cityState":"Rogers AR 72758-7027","phone":"Phone: (479) 340-0966","fax":"Fax: (479) 202-5165","webSite":"Website: "},{"name":"Adams, Howard L.","street":"2300 N Craycroft Rd Suite #4","cityState":"Tucson AZ 85712-2808","phone":"Phone: (520) 722-2992","fax":"Fax: ","webSite":"Website: "},{"name":"Adams, Irina S.","street":"14256 Ventura Blvd Ste 1","cityState":"Sherman Oaks CA 91423-2754","phone":"Phone: (818) 385-1999","fax":"Fax: (818) 385-1988","webSite":"Website: "},{"name":"Adams, James","street":"3108 W State Highway 22 ","cityState":"Corsicana TX 75110-2435","phone":"Phone: (903) 872-2448","fax":"Fax: ","webSite":"Website: "},{"name":"Adams, James E","street":"906 S Liberty St ","cityState":"Jerseyville IL 62052-2571","phone":"Phone: (618) 498-5013","fax":"Fax: (618) 498-6723","webSite":"Website: "},{"name":"Adams, James Eston","street":"19 E 3Rd St ","cityState":"Maysville KY 41056-1148","phone":"Phone: (606) 564-9033","fax":"Fax: (606) 564-9035","webSite":"Website: "},{"name":"Adams, James H","street":"329 South 9Th Street ","cityState":"Mayfield KY 42066-2211","phone":"Phone: (270) 247-2764","fax":"Fax: (270) 247-0244","webSite":"Website: "},{"name":"Adams, James L","street":"14513 S Bascom Ave #B","cityState":"Los Gatos CA 95032","phone":"Phone: (408) 356-8146","fax":"Fax: (408) 358-3614","webSite":"Website: "},{"name":"James M Adams                                                                        ","street":"750 Almar Pkwy Suite 102 Bourbonnais, IL 60914-2315"},{"name":"Adams, Jan","street":"801 University Blvd S Suite C","cityState":"Mobile AL 36609-2923","phone":"Phone: (251) 342-5323","fax":"Fax: (251) 344-8612","webSite":"Website: "},{"name":"Adams, Jared R","street":"775 Sw Bonnett Way Ste 100","cityState":"Bend OR 97702-2080","phone":"Phone: (541) 388-0078","fax":"Fax: ","webSite":"Website: "},{"name":"Adams, Jeffrey David","street":"484 North 950 West Suite C The Meadows Shopping Center","cityState":"American Fork UT 84003","phone":"Phone: (801) 756-7676","fax":"Fax: (801) 756-2171","webSite":"Website: "},{"name":"Adams, Jeffrey David","street":"1146 Kenton St ","cityState":"Bowling Green KY 42101","phone":"Phone: (270) 782-9689","fax":"Fax: ","webSite":"Website: "},{"name":"Adams, Jeffrey Floyd","street":"20185 Hwy 59 Suite 75","cityState":"New Caney TX 77357-8293","phone":"Phone: (281) 689-1888","fax":"Fax: ","webSite":"Website: "},{"name":"Adams, Jeffrey L","street":"765 Pawling Ave ","cityState":"Troy NY 12180","phone":"Phone: (518) 283-6285","fax":"Fax: (518) 283-6318","webSite":"Website: "},{"name":"Adams, Jeremy","street":"305 W 12Th Ave ","cityState":"Columbus OH 43210-1267","phone":"Phone: (614) 292-9892","fax":"Fax: ","webSite":"Website: "},{"name":"Adams, Jeremy Lynn","street":"911 Osler Dr Ste D ","cityState":"Jonesboro AR 72401-4320","phone":"Phone: (870) 935-6516","fax":"Fax: (870) 935-0188","webSite":"Website: "},{"name":"Adams, Jess G","street":"2828 International Cir Suite 100","cityState":"Colorado Springs CO 80910-3127","phone":"Phone: (719) 475-0783","fax":"Fax: ","webSite":"Website: "},{"name":"Adams, Jessica Lynn","street":"720 Olive Way Suite 810","cityState":"Seattle WA 98101","phone":"Phone: (206) 628-0404","fax":"Fax: (206) 628-0024","webSite":"Website: "},{"name":"Adams, Jill","street":"1015 Chestnut St Suite 1117","cityState":"Philadelphia PA 19107-4316","phone":"Phone: (215) 923-3999","fax":"Fax: ","webSite":"Website: "},{"name":"Adams, Jill A","street":"4379 Ridgewood Center Dr Ste 102","cityState":"Woodbridge VA 22192-8323","phone":"Phone: (703) 680-7950","fax":"Fax: (703) 680-7953","webSite":"Website: "},{"name":"Adams, Jody W,","street":"241 W Forest St ","cityState":"Brigham City UT 84302-2051","phone":"Phone: (435) 734-2547","fax":"Fax: ","webSite":"Website: "},{"name":"Adams, Joel C","street":"509 5Th St Sw ","cityState":"Cullman AL 35055-4043","phone":"Phone: (256) 338-6071","fax":"Fax: ","webSite":"Website: "},{"name":"Adams, John","street":"1724 Nebraska Ave Us Army Dentac","cityState":"Ft Leonard Wood MO 65473","phone":"Phone: (573) 596-0364","fax":"Fax: ","webSite":"Website: "},{"name":"Adams, John F.","street":"3421 Robin Ln ","cityState":"Cameron Park CA 95682-8413","phone":"Phone: (530) 677-8181","fax":"Fax: ","webSite":"Website: "},{"name":"Adams, John L","street":"317 W Cherry Ln ","cityState":"Meridian ID 83642-1608","phone":"Phone: (208) 888-2055","fax":"Fax: (208) 895-0583","webSite":"Website: "},{"name":"Adams, John S.","street":"731 W Main St ","cityState":"Fredericktown MO 63645-1113","phone":"Phone: (573) 783-4100","fax":"Fax: ","webSite":"Website: "},{"name":"Adams, John W","street":"909 E Wayne Ave ","cityState":"Salina KS 67401-2201","phone":"Phone: (785) 825-1659","fax":"Fax: ","webSite":"Website: "},{"name":"Adams, Joseph Benjamin","street":"3750 Guion Rd Ste 250 ","cityState":"Indianapolis IN 46222-1669","phone":"Phone: (317) 924-3228","fax":"Fax: ","webSite":"Website: "},{"name":"Adams, Joseph Clay","street":"2155 S Lamar Blvd ","cityState":"Oxford MS 38655-5223","phone":"Phone: (662) 234-5222","fax":"Fax: (662) 234-5254","webSite":"Website: "},{"name":"Adams, Joseph D","street":"1109 S Park Dr ","cityState":"Reidsville NC 27320-5513","phone":"Phone: (336) 342-0889","fax":"Fax: ","webSite":"Website: "},{"name":"Adams, Karen","street":"570 Riverstone Way Ste 1 ","cityState":"Fairbanks AK 99709-2940","phone":"Phone: (907) 374-7987","fax":"Fax: (907) 374-7987","webSite":"Website: "},{"name":"Adams, Kathleen A","street":"850 Statler Blvd Ste 110","cityState":"Staunton VA 24401-4885","phone":"Phone: (540) 887-3304","fax":"Fax: ","webSite":"Website: "},{"name":"Adams, Kathleene G","street":"419 Nw 23Rd Ave Suite 102","cityState":"Portland OR 97210","phone":"Phone: (503) 224-2273","fax":"Fax: (503) 224-1176","webSite":"Website: "},{"name":"Adams, Kenneth","street":"1759 Vidalia Ct ","cityState":"Greenwood IN 46143-6946","phone":"Phone: (317) 691-8838","fax":"Fax: ","webSite":"Website: "},{"name":"Adams, Kevin","street":"1100 Wilford Hall Loop Bldg 4554 ","cityState":"Jbsa Lackland TX 78236-5638","phone":"Phone: (210) 292-0755","fax":"Fax: ","webSite":"Website: "},{"name":"Adams, Kosta J","street":"2 Scripps Dr Suite 307","cityState":"Sacramento CA 95825-6207","phone":"Phone: (916) 927-0800","fax":"Fax: ","webSite":"Website: "},{"name":"Adams, Kristen Jaye","street":"2 Scripps Dr Suite 307","cityState":"Sacramento CA 95825-6207","phone":"Phone: (916) 927-0800","fax":"Fax: (916) 927-1745","webSite":"Website: "},{"name":"Adams, Kyle Warren","street":"15301 Tyler Foote Rd ","cityState":"Nevada City CA 95959-9318","phone":"Phone: (530) 292-3478","fax":"Fax: (530) 292-4296","webSite":"Website: "},{"name":"Adams, Lale O","street":"670 Colonial Rd Suite 3","cityState":"Memphis TN 38117-5160","phone":"Phone: (901) 680-6881","fax":"Fax: (901) 680-6882","webSite":"Website: "},{"name":"Adams, Larry Dean","street":"623 East University Drive ","cityState":"Mesa AZ 85203-7926","phone":"Phone: (480) 833-7070","fax":"Fax: ","webSite":"Website: "},{"name":"Adams, Larry E","street":"7730 N Union Blvd Ste 101 ","cityState":"Colorado Springs CO 80920-4075","phone":"Phone: (719) 536-0599","fax":"Fax: (719) 522-0396","webSite":"Website: "},{"name":"Adams, Larry Robert","street":"5340 Corporate Center Loop Suite A","cityState":"Lacey WA 98503","phone":"Phone: (360) 357-4578","fax":"Fax: (360) 943-4866","webSite":"Website: "},{"name":"Adams, Laura","street":"1810 E 10Th St ","cityState":"Rolla MO 65401-4603","phone":"Phone: (573) 364-1821","fax":"Fax: (573) 426-2552","webSite":"Website: "},{"name":"Adams, Laura Phillips","street":"101 East 1St Street ","cityState":"Sylacauga AL 35150","phone":"Phone: (256) 245-5635","fax":"Fax: (256) 245-5829","webSite":"Website: "},{"name":"Adams, Lauren","street":"2915 Hunter Mill Rd Suite #5","cityState":"Oakton VA 22124-1716","phone":"Phone: (703) 281-4456","fax":"Fax: ","webSite":"Website: "},{"name":"Adams, Lawrence Lyn","street":"6920 Indianapolis Blvd ","cityState":"Hammond IN 46324-2206","phone":"Phone: (219) 763-8112","fax":"Fax: (219) 764-3251","webSite":"Website: "},{"name":"Adams, Lawrence Scott","street":"3549 E Brown Rd Ste #104","cityState":"Mesa AZ 85213-5508","phone":"Phone: (480) 830-2956","fax":"Fax: (480) 830-3019","webSite":"Website: "},{"name":"Adams, Linda","street":"11382 Mountain View Ave Ste B ","cityState":"Loma Linda CA 92354-3878","phone":"Phone: (909) 796-7303","fax":"Fax: (909) 796-2784","webSite":"Website: "},{"name":"Adams, Lindsey J","street":"4036 24Th Ave ","cityState":"Fort Gratiot MI 48059-3800","phone":"Phone: (810) 385-9766","fax":"Fax: (810) 385-4161","webSite":"Website: "},{"name":"Adams, Lisa A","street":"155 Sw Century Dr Suite 102","cityState":"Bend OR 97702-1657","phone":"Phone: (541) 382-7708","fax":"Fax: ","webSite":"Website: "},{"name":"Adams, Luke Edgar","street":"611 12Th Ave S ","cityState":"Seattle WA 98144-1910","phone":"Phone: (206) 324-9360","fax":"Fax: ","webSite":"Website: "},{"name":"Adams, Lyde J","street":"1489 W Elliot Rd Ste 101 ","cityState":"Gilbert AZ 85233-5168","phone":"Phone: (480) 507-9400","fax":"Fax: ","webSite":"Website: "},{"name":"Adams, Maggie Sammons","street":"286 Palisades Dr ","cityState":"Morgantown WV 26508-9009","phone":"Phone: (304) 599-4789","fax":"Fax: ","webSite":"Website: "},{"name":"Adams, Marc D","street":"1910 Ga-20 Suite 100","cityState":"Conyers GA 30013","phone":"Phone: (770) 602-4733","fax":"Fax: ","webSite":"Website: "},{"name":"Adams, Marcie","street":"5842 Plank Rd ","cityState":"Baton Rouge LA 70805-1320","phone":"Phone: (225) 357-9200","fax":"Fax: ","webSite":"Website: "},{"name":"Adams, Marina","street":"1608 Centinela Ave 7","cityState":"Inglewood CA 90302","phone":"Phone: (310) 216-9600","fax":"Fax: (310) 216-9148","webSite":"Website: "},{"name":"Adams, Mark F","street":"1708 Missouri State Rd ","cityState":"Arnold MO 63010-2006","phone":"Phone: (636) 287-9331","fax":"Fax: ","webSite":"Website: "},{"name":"Adams, Mark William","street":"8200 E Belleview Ave Ste. 500","cityState":"Greenwood Village CO 80111-2803","phone":"Phone: (303) 988-3824","fax":"Fax: ","webSite":"Website: "},{"name":"Adams, Marlene","street":"18700 S Wolf Rd 200","cityState":"Mokena IL 60448-8456","phone":"Phone: (708) 478-8866","fax":"Fax: ","webSite":"Website: "},{"name":"Adams, Martin Michael","street":"9 E Main Street ","cityState":"Flemington NJ 08822","phone":"Phone: (908) 782-3040","fax":"Fax: (908) 782-7351","webSite":"Website: "},{"name":"Adams, Matthew","street":"3100 W Chandler Blvd Ste C ","cityState":"Chandler AZ 85226-5222","phone":"Phone: (480) 500-9991","fax":"Fax: ","webSite":"Website: "},{"name":"Adams, Matthew Reid","street":"5605 Princeton Ave Ste B","cityState":"Columbus GA 31904-9069","phone":"Phone: (706) 323-8811","fax":"Fax: (706) 323-8824","webSite":"Website: "},{"name":"Maxwell C Adams                                                                        ","street":"1000 Rohrerstown Road Lancaster, PA 17601-2644"},{"name":"Adams, Melba Karen","street":"1213 Hermann Dr Suite 265","cityState":"Houston TX 77004-7018","phone":"Phone: (713) 523-0502","fax":"Fax: (713) 523-4986","webSite":"Website: "},{"name":"Adams, Melisa Kaye","street":"11079 Columbia St ","cityState":"Blakely GA 39823-3447","phone":"Phone: (229) 724-7300","fax":"Fax: ","webSite":"Website: "},{"name":"Adams, Meredith Smith","street":"2300 Wayne Memorial Dr Suite F","cityState":"Goldsboro NC 27534-1726","phone":"Phone: (919) 734-3564","fax":"Fax: ","webSite":"Website: "},{"name":"Adams, Michael","street":"535 S Main St ","cityState":"El Dorado KS 67042-3517","phone":"Phone: (316) 321-4222","fax":"Fax: ","webSite":"Website: "},{"name":"Adams, Michael Gary","street":"307 Gretna Blvd Suite A","cityState":"Gretna LA 70053","phone":"Phone: (504) 361-5367","fax":"Fax: (504) 368-4846","webSite":"Website: "},{"name":"Adams, Michael J","street":"15 N Missouri Ave ","cityState":"Clearwater FL 33755-4830","phone":"Phone: (727) 461-4832","fax":"Fax: (727) 461-4835","webSite":"Website: "},{"name":"Adams, Michael J.","street":"5201 Haverford Ave ","cityState":"Philadelphia PA 19139-1401","phone":"Phone: (215) 471-2761","fax":"Fax: ","webSite":"Website: "},{"name":"Adams, Michael Joseph","street":"3744 Hwy 1 ","cityState":"Raceland LA 70394","phone":"Phone: (985) 537-5147","fax":"Fax: ","webSite":"Website: "},{"name":"Adams, Michael L.","street":"10708 N Western Ave Suite B","cityState":"Oklahoma City OK 73114-5830","phone":"Phone: (405) 751-7278","fax":"Fax: (405) 751-8696","webSite":"Website: "},{"name":"Adams, Michael P.","street":"107 Town Hall Sq ","cityState":"Falmouth MA 02540-2783","phone":"Phone: (508) 548-2442","fax":"Fax: (508) 457-9492","webSite":"Website: "},{"name":"Adams, Michael Padgett","street":"1314 Roanke Rd ","cityState":"Daleville VA 24083","phone":"Phone: (540) 992-1140","fax":"Fax: ","webSite":"Website: "},{"name":"Adams, Michael Stephen","street":"2302 South Union C23 ","cityState":"Tacoma WA 98405","phone":"Phone: (253) 752-8803","fax":"Fax: (253) 761-5997","webSite":"Website: "},{"name":"Adams, Mike","street":"5222 Balboa Ave Suite 71","cityState":"San Diego CA 92117-6904","phone":"Phone: (858) 279-1900","fax":"Fax: ","webSite":"Website: "},{"name":"Adams, Milton Leverett","street":"5251 Forest Dr ","cityState":"Columbia SC 29206-4920","phone":"Phone: (803) 787-9793","fax":"Fax: (803) 738-0300","webSite":"Website: "},{"name":"Adams, Mitra","street":"162 Route 59 ","cityState":"Monsey NY 10952","phone":"Phone: (845) 352-9200","fax":"Fax: (845) 352-9399","webSite":"Website: "},{"name":"Adams, Mona","street":"915 N Quincy St ","cityState":"Arlington VA 22203-1907","phone":"Phone: (703) 276-1010","fax":"Fax: ","webSite":"Website: "},{"name":"Adams, Nathan J","street":"3421 Robin Ln ","cityState":"Cameron Park CA 95682-8413","phone":"Phone: (530) 677-8181","fax":"Fax: ","webSite":"Website: "},{"name":"Adams, Nicholas V","street":"11079 Columbia St ","cityState":"Blakely GA 39823-3447","phone":"Phone: (229) 724-7300","fax":"Fax: (229) 724-7355","webSite":"Website: "},{"name":"Adams, Pamela G","street":"15 N Missouri Ave ","cityState":"Clearwater FL 33755-4830","phone":"Phone: (727) 461-4832","fax":"Fax: (727) 461-4835","webSite":"Website: "},{"name":"Adams, Patrick F","street":"818 W Broad St ","cityState":"Bethlehem PA 18018-5263","phone":"Phone: (610) 691-0160","fax":"Fax: ","webSite":"Website: "},{"name":"Adams, Patty V","street":"2821 South Hurstbourne Pkwy Ste 7","cityState":"Louisville KY 40220","phone":"Phone: (502) 493-8218","fax":"Fax: ","webSite":"Website: "},{"name":"Adams, Paul J","street":"252 Bailiwick Dr Suite 50","cityState":"Doylestown PA 18901-2422","phone":"Phone: (215) 489-8600","fax":"Fax: (215) 489-0271","webSite":"Website: "},{"name":"Adams, Peter J","street":"502 Bud Drive Ste 102","cityState":"Chesapeake VA 23322","phone":"Phone: (757) 547-0222","fax":"Fax: (757) 498-0982","webSite":"Website: "},{"name":"Adams, Phil","street":"260 Walnut St. ","cityState":"Centreville AL 35042","phone":"Phone: (205) 926-4697","fax":"Fax: (205) 926-4684","webSite":"Website: "},{"name":"Adams, Philip William","street":"9735 Wilshire Blvd Ste 432","cityState":"Beverly Hills CA 90212","phone":"Phone: (310) 276-0746","fax":"Fax: (310) 276-8414","webSite":"Website: "},{"name":"Adams, Preston Callaway","street":"5751 Pocahontas Rd Ste A ","cityState":"Bessemer AL 35022-5478","phone":"Phone: (205) 477-4242","fax":"Fax: ","webSite":"Website: "},{"name":"Adams, Priscilla Joan","street":"104 Memorial Dr ","cityState":"Gowanda NY 14070-1111","phone":"Phone: (716) 532-4022","fax":"Fax: (713) 532-2428","webSite":"Website: "},{"name":"Adams, Randall","street":"2835 E Brown Rd Ste 102 ","cityState":"Mesa AZ 85213-5470","phone":"Phone: (480) 832-3830","fax":"Fax: (480) 924-9147","webSite":"Website: "},{"name":"Adams, Randy","street":"300 W Broad St ","cityState":"Richmond VA 23220-4219","phone":"Phone: (804) 780-2888","fax":"Fax: (804) 643-1916","webSite":"Website: "},{"name":"Adams, Rex Clyne","street":"509 5Th St Sw ","cityState":"Cullman AL 35055","phone":"Phone: (256) 734-1810","fax":"Fax: (256) 734-1843","webSite":"Website: "},{"name":"Adams, Rex Mckinley","street":"513 5Th St Sw ","cityState":"Cullman AL 35055-4043","phone":"Phone: (256) 734-6071","fax":"Fax: (256) 734-6101","webSite":"Website: "},{"name":"Adams, Richard Clayton","street":"413 Owens Drive Suite 102","cityState":"Fayetteville NC 28304","phone":"Phone: (910) 496-9400","fax":"Fax: (910) 496-9402","webSite":"Website: "},{"name":"Adams, Richard Kenney","street":"8072 W Sahara Ave Suite B","cityState":"Las Vegas NV 89117-1974","phone":"Phone: (702) 363-0757","fax":"Fax: ","webSite":"Website: "},{"name":"Adams, Richard Taylor","street":"3701 Baker Ln Suite #1","cityState":"Reno NV 89509-5412","phone":"Phone: (775) 825-1000","fax":"Fax: (775) 826-3030","webSite":"Website: "},{"name":"Adams, Rick","street":"106 W. Palisade Ave. Suite 202 ","cityState":"Englewood NJ 07637","phone":"Phone: (201) 567-3078","fax":"Fax: (201) 567-3098","webSite":"Website: "},{"name":"Adams, Riley Scott","street":"813 Stilson Rd.; Suite B Millennium Family Dental- Boise Llc","cityState":"Boise ID 83703","phone":"Phone: (208) 888-2026","fax":"Fax: (208) 888-2094","webSite":"Website: "},{"name":"Adams, Robert","street":"5220 W Washington Blvd Suite 103","cityState":"Los Angeles CA 90016-1331","phone":"Phone: (323) 933-5641","fax":"Fax: (323) 939-6620","webSite":"Website: "},{"name":"Adams, Robert Allen","street":"188 River Vista Pl ","cityState":"Twin Falls ID 83301-3056","phone":"Phone: (208) 733-2090","fax":"Fax: (208) 732-8369","webSite":"Website: "},{"name":"Adams, Robert C","street":"55 Cherry St ","cityState":"Milford CT 06460-8903","phone":"Phone: (203) 877-7671","fax":"Fax: ","webSite":"Website: "},{"name":"Adams, Robert J","street":"540 W Lasalle St ","cityState":"Springfield MO 65807-4712","phone":"Phone: (417) 887-1220","fax":"Fax: (417) 887-0357","webSite":"Website: "},{"name":"Adams, Robert Lewis","street":"12 Carnoustie Cir. ","cityState":"Bloomfield CT 06002","phone":"Phone: (860) 286-0652","fax":"Fax: ","webSite":"Website: "},{"name":"Adams, Robert Muse","street":"81 North Main St. ","cityState":"Marshall NC 28753","phone":"Phone: (828) 649-2621","fax":"Fax: (828) 649-3704","webSite":"Website: "},{"name":"Adams, Robert R","street":"3410 Mccall Avenue Suite 102 ","cityState":"Selma CA 93662-2500","phone":"Phone: (559) 896-5011","fax":"Fax: (559) 896-5410","webSite":"Website: "},{"name":"Adams, Robert Waggoner","street":"501 S Hughes St ","cityState":"Hamilton MO 64644-8230","phone":"Phone: (816) 583-2750","fax":"Fax: (816) 583-2934","webSite":"Website: "},{"name":"Adams, Robyn K","street":"2250 Thousand Oaks Dr Suite 120","cityState":"San Antonio TX 78232-3989","phone":"Phone: (724) 657-4623","fax":"Fax: ","webSite":"Website: "},{"name":"Adams, Roderick Henry","street":"1464 E 105Th St Ste 203","cityState":"Cleveland OH 44106-1100","phone":"Phone: (216) 421-6000","fax":"Fax: (216) 421-1627","webSite":"Website: "},{"name":"Adams, Roger J","street":"5373 Green St Suite 400","cityState":"Salt Lake City UT 84123-4680","phone":"Phone: (801) 313-7051","fax":"Fax: (801) 290-5126","webSite":"Website: "},{"name":"Adams, Roland","street":"1001 Sw 5Th Ave Suite 222","cityState":"Portland OR 97204-1147","phone":"Phone: (503) 222-5355","fax":"Fax: ","webSite":"Website: "},{"name":"Adams, Ronald M.","street":"708 Dunbar Rd ","cityState":"Warner Robins GA 31093-1002","phone":"Phone: (478) 929-8622","fax":"Fax: (478) 918-0253","webSite":"Website: "},{"name":"Adams, Ryan","street":"1285 Virgil Langford Rd ","cityState":"Watkinsville GA 30677-7209","phone":"Phone: (706) 521-0352","fax":"Fax: ","webSite":"Website: "},{"name":"Adams, Salman","street":"415 Avenel St ","cityState":"Avenel NJ 07001","phone":"Phone: (732) 636-7866","fax":"Fax: (732) 636-7887","webSite":"Website: "},{"name":"Adams, Samuel H.","street":"3735 Drexel Dr Ste. C","cityState":"Houston TX 77027-6896","phone":"Phone: (713) 623-2260","fax":"Fax: (713) 623-6152","webSite":"Website: "},{"name":"Adams, Scott Ernest","street":"1710 E March Ln Ste 2B","cityState":"Stockton CA 95210-5665","phone":"Phone: (209) 474-1000","fax":"Fax: (209) 474-8429","webSite":"Website: "},{"name":"Adams, Scott Michael","street":"2458 E 146Th St ","cityState":"Carmel IN 46033-7712","phone":"Phone: (317) 815-6670","fax":"Fax: (317) 815-6689","webSite":"Website: "},{"name":"Adams, Stephen Earl","street":"1171 E Bixby Rd ","cityState":"Long Beach CA 90807-4125","phone":"Phone: (562) 595-9131","fax":"Fax: (562) 989-6864","webSite":"Website: "},{"name":"Adams, Stephen Wilford","street":"14562 Us Highway 160 ","cityState":"Forsyth MO 65653-8112","phone":"Phone: (417) 546-4507","fax":"Fax: ","webSite":"Website: "},{"name":"Adams, Steven Robert","street":"26 Reynolds Mountain Blvd ","cityState":"Asheville NC 28804-1270","phone":"Phone: (828) 658-2100","fax":"Fax: (828) 645-6513","webSite":"Website: "},{"name":"Adams, Susan S","street":"1321 Veterans Blvd ","cityState":"Festus MO 63028-2329","phone":"Phone: (636) 931-4020","fax":"Fax: ","webSite":"Website: "},{"name":"Adams, Tabatha Mann","street":"1508 Oxford Dr ","cityState":"Georgetown KY 40324-9266","phone":"Phone: (502) 863-0880","fax":"Fax: (502) 867-7363","webSite":"Website: "},{"name":"Adams, Tammie Lajuana","street":"20707 Anza Ave Apt # 271","cityState":"Torrance CA 90503-2925","phone":"Phone: (424) 247-7235","fax":"Fax: ","webSite":"Website: "},{"name":"Adams, Tamra M","street":"920 Northgate Dr Suite 7","cityState":"San Rafael CA 94903-3429","phone":"Phone: (415) 472-2870","fax":"Fax: (415) 472-2871","webSite":"Website: "},{"name":"Adams, Terry B","street":"8201 Preston Rd Suite 555","cityState":"Dallas TX 75225-6203","phone":"Phone: (214) 369-0972","fax":"Fax: (214) 369-1044","webSite":"Website: "},{"name":"Adams, Thomas J","street":"330 W Frontage Rd Suite 2W","cityState":"Northfield IL 60093-3467","phone":"Phone: (847) 784-5555","fax":"Fax: (847) 784-5557","webSite":"Website: "},{"name":"Adams, Thomas James","street":"9330 Carmel Mountain Rd Suite D","cityState":"San Diego CA 92129-2157","phone":"Phone: (858) 484-6100","fax":"Fax: (858) 484-8601","webSite":"Website: "},{"name":"Adams, Thomas Nelson","street":"2615 Anderson Hwy ","cityState":"Powhatan VA 23139","phone":"Phone: (804) 598-3000","fax":"Fax: (804) 598-9874","webSite":"Website: "},{"name":"Adams, Thomas Olin","street":"4224 Houma Blvd Ste 224 ","cityState":"Metairie LA 70006-2935","phone":"Phone: (504) 454-4224","fax":"Fax: (504) 456-5122","webSite":"Website: "},{"name":"Adams, Thomas W.","street":"116 W Superior St ","cityState":"Munising MI 49862-1124","phone":"Phone: (906) 387-4200","fax":"Fax: (906) 387-4201","webSite":"Website: "},{"name":"Adams, Thomas Zachary","street":"1548 Wildcat Dr ","cityState":"Portland TX 78374-2814","phone":"Phone: (361) 777-0700","fax":"Fax: ","webSite":"Website: "},{"name":"Adams, Timothy Alan","street":"1500 Alafaya Trl Ste 1064 ","cityState":"Oviedo FL 32765-4517","phone":"Phone: (407) 977-1600","fax":"Fax: ","webSite":"Website: "},{"name":"Adams, Timothy C","street":"1040 N Rangeline Rd Ste B ","cityState":"Carmel IN 46032-1470","phone":"Phone: (317) 580-9222","fax":"Fax: (317) 580-9226","webSite":"Website: "},{"name":"Adams, Timothy Cid","street":"59 Damonte Ranch Pkwy Ste F ","cityState":"Reno NV 89521-2989","phone":"Phone: (775) 851-2204","fax":"Fax: ","webSite":"Website: "},{"name":"Adams, Timothy James","street":"3734 N Arkansas Ave ","cityState":"Wichita KS 67204-4053","phone":"Phone: (316) 838-1101","fax":"Fax: ","webSite":"Website: "},{"name":"Adams, Timothy M","street":"7 Southwoods Blvd ","cityState":"Albany NY 12211-2514","phone":"Phone: (518) 455-2505","fax":"Fax: ","webSite":"Website: "},{"name":"Adams, Timothy Wayne","street":"695 S Colorado Blvd Suite 250","cityState":"Denver CO 80246-8008","phone":"Phone: (303) 733-7731","fax":"Fax: (303) 733-7283","webSite":"Website: "},{"name":"Adams, Todd","street":"166 Winslow Way W ","cityState":"Bainbridge Island WA 98110-2512","phone":"Phone: (206) 842-0324","fax":"Fax: ","webSite":"Website: "},{"name":"Adams, Todd","street":"55 E Julian St ","cityState":"San Jose CA 95112-4007","phone":"Phone: (408) 918-2618","fax":"Fax: ","webSite":"Website: "},{"name":"Adams, Tracy L","street":"509 Olive Way Suite 1242","cityState":"Seattle WA 98101-1720","phone":"Phone: (206) 623-5546","fax":"Fax: (206) 623-6055","webSite":"Website: "},{"name":"Adams, Travis B","street":"855 W Seventh St Ste 200","cityState":"Reno NV 89503","phone":"Phone: (775) 800-5543","fax":"Fax: (775) 309-4163","webSite":"Website: "},{"name":"Adams, Trenton","street":"23185 Hemlock Ave ","cityState":"Moreno Valley CA 92557-8043","phone":"Phone: (951) 571-8369","fax":"Fax: ","webSite":"Website: "},{"name":"Adams, Vernon James","street":"750 Welch Rd Suite 102","cityState":"Palo Alto CA 94304-1507","phone":"Phone: (650) 321-6448","fax":"Fax: (650) 321-5277","webSite":"Website: "},{"name":"Adams, William","street":"4315 Grove Avenue ","cityState":"Richmond VA 23221","phone":"Phone: (804) 285-1378","fax":"Fax: (804) 285-1388","webSite":"Website: "},{"name":"Adams, William","street":"2644 Mosside Blvd ","cityState":"Monroeville PA 15146-3348","phone":"Phone: (412) 856-7270","fax":"Fax: (412) 856-6521","webSite":"Website: "},{"name":"Adams, William Andrew","street":"104 Carlisle St Suite 2","cityState":"Hanover PA 17331-2406","phone":"Phone: (717) 630-2343","fax":"Fax: (717) 630-2950","webSite":"Website: "},{"name":"Adams, William Claybrooke","street":"8835 Us Highway 431 ","cityState":"Albertville AL 35950-0161","phone":"Phone: (256) 878-2380","fax":"Fax: (256) 878-2415","webSite":"Website: "},{"name":"Adams, William Joseph","street":"59 Crystal Spring Ave ","cityState":"North Falmouth MA 02556-2606","phone":"Phone: (508) 563-5052","fax":"Fax: ","webSite":"Website: "},{"name":"Adams, William R","street":"3750 Guion Rd Suite 280","cityState":"Indianapolis IN 46222-7602","phone":"Phone: (317) 924-3228","fax":"Fax: ","webSite":"Website: "},{"name":"Adams, William W","street":"211 Harley St ","cityState":"Jonesville MI 49250","phone":"Phone: (517) 849-9195","fax":"Fax: (517) 849-9611","webSite":"Website: "},{"name":"Adams, Yasmin Sarah","street":"2299 Brodhead Rd ","cityState":"Bethlehem PA 18020","phone":"Phone: (610) 866-0172","fax":"Fax: ","webSite":"Website: "},{"name":"Adams,Jr., James Wayne","street":"2810 Halifax Rd ","cityState":"South Boston VA 24592-5120","phone":"Phone: (434) 575-7894","fax":"Fax: ","webSite":"Website: "},{"name":"Adams-Feeney, Shawna C","street":"15293 Amberly Dr ","cityState":"Tampa FL 33647-2155","phone":"Phone: (813) 631-1100","fax":"Fax: (813) 631-1644","webSite":"Website: "},{"name":"Adams-Smith, Sandra","street":"343 Commercial Dr ","cityState":"Savannah GA 31406-3606","phone":"Phone: (912) 355-5437","fax":"Fax: ","webSite":"Website: "},{"name":"Adams-Williams, Cheryl Denise","street":"2 E Rolling Crossroads Ste 57","cityState":"Catonsville MD 21228-6211","phone":"Phone: (410) 747-1830","fax":"Fax: (410) 747-1823","webSite":"Website: "},{"name":"Adamski, Brian","street":"128 County Line Rd W Ste B ","cityState":"Westerville OH 43082-7222","phone":"Phone: (419) 349-2718","fax":"Fax: ","webSite":"Website: "},{"name":"Adamski, Joanne R","street":"881 Uss James Madison Rd ","cityState":"Kings Bay GA 31547-2531","phone":"Phone: (912) 573-3327","fax":"Fax: ","webSite":"Website: "},{"name":"Adamson, Aaron Urban","street":"290 Brinkby Ave Ste. 1","cityState":"Reno NV 89509-4348","phone":"Phone: (775) 826-7833","fax":"Fax: (775) 826-6017","webSite":"Website: "},{"name":"Adamson, Anne C","street":"4014 Lake St Ste 210 ","cityState":"Homer AK 99603-7692","phone":"Phone: (907) 235-7585","fax":"Fax: ","webSite":"Website: "},{"name":"Adamson, Dennis N","street":"480 W 800 N ","cityState":"Orem UT 84057-3745","phone":"Phone: (801) 224-1200","fax":"Fax: ","webSite":"Website: "},{"name":"Adamson, Erin M","street":"1962 Scotland Ave ","cityState":"Chambersburg PA 17201-1450","phone":"Phone: (717) 263-8288","fax":"Fax: (717) 263-2398","webSite":"Website: "},{"name":"Adamson, James R","street":"115 K D Revell Rd ","cityState":"Wauchula FL 33873-2051","phone":"Phone: (863) 773-4161","fax":"Fax: (863) 773-5056","webSite":"Website: "},{"name":"Adamson, Jeffrey Paul","street":"3280 West 3500 South Suite 1","cityState":"West Valley City UT 84119-2694","phone":"Phone: (801) 968-6331","fax":"Fax: (801) 968-0500","webSite":"Website: "},{"name":"Adamson, Jesse Joseph","street":"1667 Cochrane Cir Bldg 7495 ","cityState":"Fort Carson CO 80913-4603","phone":"Phone: (719) 526-5537","fax":"Fax: ","webSite":"Website: "},{"name":"Adamson, Kurt B","street":"2997 Hope Mills Rd Suite C","cityState":"Fayetteville NC 28306-8349","phone":"Phone: (910) 426-0800","fax":"Fax: ","webSite":"Website: "},{"name":"Adamson, Lori Marie","street":"570 Brandies Cir ","cityState":"Murfreesboro TN 37128-7687","phone":"Phone: (615) 896-8181","fax":"Fax: (615) 896-8848","webSite":"Website: "},{"name":"Adamson, Morgan Nicole","street":"140 Mahaley Ave Ste B ","cityState":"Salisbury NC 28144-2449","phone":"Phone: (704) 637-5506","fax":"Fax: ","webSite":"Website: "},{"name":"Adamson, Neil D","street":"270 E 5Th N ","cityState":"Mountain Home ID 83647-2749","phone":"Phone: (208) 587-9031","fax":"Fax: (208) 587-9031","webSite":"Website: "},{"name":"Adamson, Nikole Dawn","street":"230 Riverstone Pkwy Ste A ","cityState":"Canton GA 30114-6414","phone":"Phone: (770) 479-5425","fax":"Fax: (770) 479-0291","webSite":"Website: "},{"name":"Adamson, Stephen Joseph","street":"3491 Anderson Hill Road ","cityState":"Silverdale WA 98383","phone":"Phone: (360) 692-8600","fax":"Fax: (360) 692-5364","webSite":"Website: "},{"name":"Adamson, Timothy Paul","street":"1962 Scotland Ave ","cityState":"Chambersburg PA 17201-1450","phone":"Phone: (717) 263-8288","fax":"Fax: (717) 263-2398","webSite":"Website: "},{"name":"Adamson, William Fletcher","street":"31 W 100 S Ste B ","cityState":"Pleasant Grove UT 84062-2641","phone":"Phone: (801) 785-2821","fax":"Fax: ","webSite":"Website: "},{"name":"Adamushko-Fili, Carylee Alexandria","street":"2225 N Jerusalem Rd ","cityState":"East Meadow NY 11554-5157","phone":"Phone: (516) 481-4111","fax":"Fax: ","webSite":"Website: "},{"name":"Adan, Cirilo Lagmay","street":"90 Via Juana Lane Santa Ynez Tribal Health Clinic","cityState":"Santa Ynez CA 93460","phone":"Phone: (805) 688-7070","fax":"Fax: (805) 686-2060","webSite":"Website: "},{"name":"Adan, Judy Ann","street":"8300 N Fm 620, Bldg G Ste 100 ","cityState":"Austin TX 78726","phone":"Phone: (512) 331-0359","fax":"Fax: ","webSite":"Website: "},{"name":"Adan-Rice, Delhi","street":"19585 K St ","cityState":"Somerset TX 78069-4478","phone":"Phone: (830) 429-3000","fax":"Fax: (830) 429-3005","webSite":"Website: "},{"name":"Adapalli, Arvind Prashanth","street":"2730 Sw Moody Ave ","cityState":"Portland OR 97201-5042","phone":"Phone: (503) 494-8867","fax":"Fax: ","webSite":"Website: "},{"name":"Adaptive Dental Associates Llc","street":"755 Memorial Pkwy Suite 301","cityState":"Phillipsburg NJ 08865-2748","phone":"Phone: (908) 859-4498","fax":"Fax: (908) 387-0767","webSite":"Website: "},{"name":"Healthy Smile","street":"10070-D Jose Clementa Orozco Zona Rio","cityState":"Tijuana BAJA CALIFORNIA 22000","phone":"Phone: (664) 687-4332","fax":"Fax: ","webSite":"Website: "},{"name":"Adarmes, Arnedith","street":"2011 W 62Nd St ","cityState":"Hialeah FL 33016-2657","phone":"Phone: (352) 363-4969","fax":"Fax: ","webSite":"Website: "},{"name":"Adarve, Ranier M","street":"611 Sw Campus Dr Room 19","cityState":"Portland OR 97239-3001","phone":"Phone: (503) 494-4316","fax":"Fax: (503) 494-8384","webSite":"Website: "},{"name":"Adashek, Scott Daniel","street":"2080 E Williams Field Rd Ste 104 ","cityState":"Gilbert AZ 85295","phone":"Phone: (480) 284-6402","fax":"Fax: (480) 621-7022","webSite":"Website: "},{"name":"Adatia, Anand","street":"11100 Parkfield Dr ","cityState":"Austin TX 78758-4263","phone":"Phone: (512) 339-7848","fax":"Fax: (512) 339-7862","webSite":"Website: "},{"name":"Adatia, Mayank R","street":"853 N Highland Ave Suite C","cityState":"Aurora IL 60506-2217","phone":"Phone: (630) 844-3368","fax":"Fax: (630) 844-2873","webSite":"Website: "},{"name":"Adatia, Nimet","street":"2029 Valleygate Dr Suite 201","cityState":"Fayetteville NC 28304-3688","phone":"Phone: (910) 485-8884","fax":"Fax: ","webSite":"Website: "},{"name":"Adatia, Shakuntala M","street":"359 N Farnsworth Ave ","cityState":"Aurora IL 60505-3082","phone":"Phone: (847) 769-4133","fax":"Fax: (630) 544-5708","webSite":"Website: "},{"name":"Adatrow, Pradeep","street":"7135 Getwell Rd Ste 100 ","cityState":"Southaven MS 38672-9659","phone":"Phone: (662) 655-4868","fax":"Fax: ","webSite":"Website: "},{"name":"Adatto, Larry Jay","street":"7347 35Th Ave Ne Suite C","cityState":"Seattle WA 98115-5987","phone":"Phone: (206) 526-9040","fax":"Fax: ","webSite":"Website: "},{"name":"Adaven Childrens Dentistry","street":"1701 N Green Valley Parkway #8E","cityState":"Henderson NV 89074","phone":"Phone: (702) 492-1955","fax":"Fax: (702) 492-7663","webSite":"Website: "},{"name":"Aday Orthodontics, Pc","street":"2701 Missouri Ave. Suite D","cityState":"Las Cruces NM 88011","phone":"Phone: (575) 522-1500","fax":"Fax: (575) 521-1529","webSite":"Website: "},{"name":"Aday, B Joe","street":"2701 Missouri Ave Ste D ","cityState":"Las Cruces NM 88011-5091","phone":"Phone: (505) 522-1500","fax":"Fax: (505) 521-1529","webSite":"Website: "},{"name":"Aday, James Bradley","street":"2701 Missouri Ave Ste E ","cityState":"Las Cruces NM 88011-5091","phone":"Phone: (575) 522-2000","fax":"Fax: ","webSite":"Website: "},{"name":"Aday, Phillip Lynn","street":"1116 Nw Arlington ","cityState":"Lawton OK 73507","phone":"Phone: (580) 248-2225","fax":"Fax: (580) 355-7289","webSite":"Website: "},{"name":"Astoria Denture Clinic","street":"720 Bennett Ave ","cityState":"Medford OR 97504-6722","phone":"Phone: (541) 772-8280","fax":"Fax: (541) 734-7771","webSite":"Website: "},{"name":"Adc Miller Square Pl","street":"13840 Sw 56Th St ","cityState":"Miami FL 33175-6061","phone":"Phone: (305) 387-6453","fax":"Fax: ","webSite":"Website: "},{"name":"Adc Serives:Dental Pc","street":"12921 West Bellfort ","cityState":"Sugar Land TX 77478","phone":"Phone: (281) 240-1177","fax":"Fax: ","webSite":"Website: "},{"name":"Allied Family Dentistry","street":"11001 Fondren Rd # B","cityState":"Houston TX 77096-5594","phone":"Phone: (713) 773-9800","fax":"Fax: (713) 773-9804","webSite":"Website: "},{"name":"Adc Ventures","street":"4041 Highway 90 ","cityState":"Pace FL 32571-1917","phone":"Phone: (850) 994-8185","fax":"Fax: ","webSite":"Website: "},{"name":"Neptune Dental Care","street":"2200 Hwy 66 Suite 8","cityState":"Neptune NJ 07753-4062","phone":"Phone: (732) 775-7800","fax":"Fax: (732) 775-7877","webSite":"Website: "},{"name":"Adcock, Carmen Overstreet","street":"125 Jefferson Davis Blvd ","cityState":"Natchez MS 39120-5103","phone":"Phone: (601) 442-0250","fax":"Fax: (601) 442-2448","webSite":"Website: "},{"name":"Adcock, Jeffrey Michael","street":"7342 Oak Manor Dr #4203","cityState":"San Antonio TX 78229-4543","phone":"Phone: (210) 216-0636","fax":"Fax: ","webSite":"Website: "},{"name":"Adcock, John E.","street":"3805 Brookside Dr ","cityState":"Tyler TX 75701-9421","phone":"Phone: (903) 288-8805","fax":"Fax: (903) 509-0160","webSite":"Website: "},{"name":"Adcock, Micah Danielle","street":"440 E Tampa St ","cityState":"Springfield MO 65806-1131","phone":"Phone: (417) 831-0150","fax":"Fax: (417) 868-8263","webSite":"Website: "},{"name":"Adcock, Phillip","street":"1520 Lucky St ","cityState":"Griffin GA 30223-1176","phone":"Phone: (770) 227-0223","fax":"Fax: (770) 228-5564","webSite":"Website: "},{"name":"Adcock, Scott A","street":"2904 N 4Th St Ste 106","cityState":"Longview TX 75605-5129","phone":"Phone: (903) 758-3700","fax":"Fax: (903) 234-8658","webSite":"Website: "},{"name":"Adcook, Richard Scott","street":"Naval Hospital Charleston ","cityState":"North Charleston SC 29405","phone":"Phone: (843) 743-7868","fax":"Fax: (843) 743-7521","webSite":"Website: "},{"name":"Adcox, Joshua Darrell","street":"2113 Sw H K Dodgen Loop ","cityState":"Temple TX 76502-1849","phone":"Phone: (480) 388-1661","fax":"Fax: ","webSite":"Website: "},{"name":"Addabbo, Frank Michael","street":"6001 Vineland Rd Ste 119 ","cityState":"Orlando FL 32819-7829","phone":"Phone: (407) 352-6001","fax":"Fax: (407) 351-2864","webSite":"Website: "},{"name":"Rocco R Addante                                                                        ","street":"1 Medical Center Dr Dartmouth Hitchcock Medical Center -oral Surgery Lebanon, NH 03756-1000"},{"name":"Addario, Nicolo","street":"1351 Medical Center Dr Suite B","cityState":"Chula Vista CA 91911-6977","phone":"Phone: (619) 656-1788","fax":"Fax: (619) 656-1786","webSite":"Website: "},{"name":"Addas, Abdul-Rahman Addas","street":"23 Cedar St ","cityState":"Taunton MA 02780-3330","phone":"Phone: (508) 822-1281","fax":"Fax: ","webSite":"Website: "},{"name":"Addax Dental Pllc","street":"546 E Market St ","cityState":"Leesburg VA 20176-4112","phone":"Phone: (703) 777-5939","fax":"Fax: ","webSite":"Website: "},{"name":"Addeo, Paul","street":"14204 Bayside Ave Suite 2U","cityState":"Flushing NY 11354-2331","phone":"Phone: (718) 539-6655","fax":"Fax: ","webSite":"Website: "},{"name":"Adderley Dental Group","street":"7826 Eastern Ave Nw Ste 202 ","cityState":"Washington DC 20012-1333","phone":"Phone: (202) 722-1731","fax":"Fax: (202) 722-1640","webSite":"Website: "},{"name":"Adderley, Toni Louise","street":"7826 Eastern Ave Nw Ste 202 ","cityState":"Washington DC 20012-1333","phone":"Phone: (202) 722-1731","fax":"Fax: (202) 722-1640","webSite":"Website: "},{"name":"Adderly, Erica Juliet","street":"3038 Nolensville Pike ","cityState":"Nashville TN 37211-2337","phone":"Phone: (615) 331-2483","fax":"Fax: (615) 834-7179","webSite":"Website: "},{"name":"Addevale Family Dentistry, P.C.","street":"210 Addavale St ","cityState":"Griffin GA 30224-4217","phone":"Phone: (770) 229-1490","fax":"Fax: ","webSite":"Website: "},{"name":"Addicks, Earl Melvin","street":"2025 Suffolk Rd Suite 12","cityState":"Finksburg MD 21048-1633","phone":"Phone: (410) 526-4750","fax":"Fax: (410) 526-4786","webSite":"Website: "},{"name":"Cedar Creek Dental","street":"950 Atlantic City Blvd Suite 13","cityState":"Bayville NJ 08721-3564","phone":"Phone: (732) 269-1046","fax":"Fax: ","webSite":"Website: "},{"name":"Addiego, Domenico","street":"220 Route 72 W ","cityState":"Manahawkin NJ 08050-2812","phone":"Phone: (609) 597-4660","fax":"Fax: (609) 597-4771","webSite":"Website: "},{"name":"Addiego, Lynne Julia","street":"161 Us Route 302 - Berlin ","cityState":"Barre VT 05641","phone":"Phone: (802) 476-8700","fax":"Fax: ","webSite":"Website: "},{"name":"Addiego, Nicholas","street":"810 Barnegat Ave Ste A Suite A","cityState":"Ship Bottom NJ 08008-4686","phone":"Phone: (609) 361-2900","fax":"Fax: (609) 361-2902","webSite":"Website: "},{"name":"Addiego, Teresa","street":"560A Lippincott Drive ","cityState":"Marlton NJ 08053-4808","phone":"Phone: (856) 985-1800","fax":"Fax: (856) 985-7170","webSite":"Website: "},{"name":"Addington, Amy H","street":"418 E New Haven Ave ","cityState":"Melbourne FL 32901","phone":"Phone: (321) 722-3337","fax":"Fax: (321) 722-9951","webSite":"Website: "},{"name":"Addington, Danny Warren","street":"307 East Hiram ","cityState":"Atlanta TX 75551","phone":"Phone: (903) 796-2111","fax":"Fax: (903) 796-5401","webSite":"Website: "},{"name":"Addington, Jerry Wayne","street":"112 Falcon Drive ","cityState":"Fredericksburg VA 22408","phone":"Phone: (540) 898-8194","fax":"Fax: (540) 898-6334","webSite":"Website: "},{"name":"Addington, Mark R","street":"2 Woodmont Crossing ","cityState":"Texarkana TX 75503","phone":"Phone: (903) 792-6613","fax":"Fax: (903) 792-6401","webSite":"Website: "},{"name":"Addink, Ken L","street":"159 S Main Ave ","cityState":"Sioux Center IA 51250-1535","phone":"Phone: (712) 722-2618","fax":"Fax: (712) 722-2638","webSite":"Website: "},{"name":"Addis, Julie K.","street":"804 Palm Dr ","cityState":"Dublin GA 31021-5634","phone":"Phone: (478) 272-1983","fax":"Fax: ","webSite":"Website: "},{"name":"Addison, Clarence","street":"4045 Orchard Rd Se Ste 300 ","cityState":"Smyrna GA 30080-4900","phone":"Phone: (770) 433-0445","fax":"Fax: ","webSite":"Website: "},{"name":"Addison, Edward","street":"110 William St ","cityState":"Newark NJ 07102-1304","phone":"Phone: (973) 733-7590","fax":"Fax: ","webSite":"Website: "},{"name":"Addison, John","street":"9700 S Dixie Hwy Suite 910","cityState":"Miami FL 33156-2800","phone":"Phone: (305) 670-9755","fax":"Fax: (305) 670-9757","webSite":"Website: "},{"name":"Addison, Samuel N","street":"8305 Falls Of Neuse Rd Ste 105 ","cityState":"Raleigh NC 27615-3546","phone":"Phone: (919) 841-1720","fax":"Fax: (919) 841-1725","webSite":"Website: "},{"name":"Addison, Taylor","street":"10833 Le Conte Ave Rm 20-137 ","cityState":"Los Angeles CA 90095-3075","phone":"Phone: (310) 825-5619","fax":"Fax: ","webSite":"Website: "},{"name":"Addleson, Lawrence M","street":"2840 5Th Ave 300","cityState":"San Diego CA 92103-6331","phone":"Phone: (619) 291-4325","fax":"Fax: (619) 291-2578","webSite":"Website: "},{"name":"Addona, C. Donald","street":"4 White Springs Cir ","cityState":"Geneva NY 14456-3008","phone":"Phone: (315) 789-6057","fax":"Fax: ","webSite":"Website: "},{"name":"Addonizio, Mary Kathleen","street":"26932 Oso Pkwy Suite 210","cityState":"Mission Viejo CA 92691-5815","phone":"Phone: (949) 582-2325","fax":"Fax: (949) 582-8631","webSite":"Website: "},{"name":"Addvensky, Laurie","street":"79 W Ridgewood Ave ","cityState":"Ridgewood NJ 07450-3142","phone":"Phone: (201) 652-0060","fax":"Fax: (201) 652-7687","webSite":"Website: "},{"name":"Addy, Drew Kevin","street":"1184 W 30Th St Apartment #8","cityState":"Los Angeles CA 90007-3183","phone":"Phone: (213) 925-0210","fax":"Fax: ","webSite":"Website: "},{"name":"Addy, Eldean C","street":"2617 Loma Vista Rd ","cityState":"Ventura CA 93003-1548","phone":"Phone: (805) 643-4704","fax":"Fax: ","webSite":"Website: "},{"name":"Addy, Nancy L","street":"11313 Ash St ","cityState":"Leawood KS 66211-1643","phone":"Phone: (913) 451-2929","fax":"Fax: (913) 451-2959","webSite":"Website: "},{"name":"Adea, Christian","street":"206 Ne 7Th Ave ","cityState":"Amarillo TX 79107-5214","phone":"Phone: (806) 318-3908","fax":"Fax: ","webSite":"Website: "},{"name":"Adebayo, Albert Olugbenga","street":"7033 S Merrill Ave Apt 203","cityState":"Chicago IL 60649-2109","phone":"Phone: (773) 592-9646","fax":"Fax: ","webSite":"Website: "},{"name":"Adebayo, Loni Nicol","street":"5637 W Fullerton Ave ","cityState":"Chicago IL 60639-2351","phone":"Phone: (708) 951-0637","fax":"Fax: ","webSite":"Website: "},{"name":"Adebimpe Bebe Ibitayo Dds Ms Pllc","street":"106 Rose Gdn ","cityState":"Universal City TX 78148-3422","phone":"Phone: (210) 658-2251","fax":"Fax: ","webSite":"Website: "},{"name":"Adedara, Isaac Olumide","street":"8605 Cameron St Ste 208 ","cityState":"Silver Spring MD 20910-3728","phone":"Phone: (301) 588-6060","fax":"Fax: (301) 588-6088","webSite":"Website: "},{"name":"Adedeji, Iseoluwa Adebola","street":"7703 Floyd Curl Dr Uthscsa Department Of Community Dentistry, Msc 7917","cityState":"San Antonio TX 78229-3901","phone":"Phone: (210) 567-3200","fax":"Fax: (210) 567-4587","webSite":"Website: "},{"name":"Adedoyin, Olajumoke O","street":"4484 Jimmy Lee Smith Pkwy Suite E114","cityState":"Hiram GA 30141-2737","phone":"Phone: (770) 222-7818","fax":"Fax: (770) 222-7828","webSite":"Website: "},{"name":"Adeeb, Ayman Kedes","street":"500 W Jubel Early Dr Suite Number 200","cityState":"Winchester VA 22601","phone":"Phone: (540) 535-2006","fax":"Fax: ","webSite":"Website: "},{"name":"Happy Chompers Pediatric Dentistry","street":"23302 W Fernhurst Drive Suite 200","cityState":"Katy TX 77494","phone":"Phone: (832) 559-2370","fax":"Fax: ","webSite":"Website: "},{"name":"Adegoke, Denise","street":"500 E Plaza Dr Ste 1 ","cityState":"Carterville IL 62918-2009","phone":"Phone: (618) 985-4200","fax":"Fax: ","webSite":"Website: "},{"name":"Adegun, Oreoluwa Anuoluwapo","street":"10260 Westheimer Rd ","cityState":"Houston TX 77042-3110","phone":"Phone: (832) 620-8516","fax":"Fax: ","webSite":"Website: "},{"name":"Adeinat, Bashar","street":"1340 Blanding Blvd Ste 108 ","cityState":"Orange Park FL 32065","phone":"Phone: (904) 639-6924","fax":"Fax: ","webSite":"Website: "},{"name":"Adekola, Ademola Jimoh","street":"955 W Monroe St ","cityState":"Chicago IL 60607-2811","phone":"Phone: (312) 994-4460","fax":"Fax: ","webSite":"Website: "},{"name":"Adekugbe, Olubunmi","street":"7891 Broadway ","cityState":"Merrillville IN 46410-5556","phone":"Phone: (219) 736-2273","fax":"Fax: ","webSite":"Website: "},{"name":"Adel Family Dentistry, P.C.","street":"1126 Greene St ","cityState":"Adel IA 50003-1712","phone":"Phone: (515) 993-3701","fax":"Fax: (515) 993-3701","webSite":"Website: "},{"name":"Adel Khalil D.D.S., M.D. P.C.","street":"2435 Webster St Ste 200 ","cityState":"Berkeley CA 94705-2050","phone":"Phone: (510) 548-9114","fax":"Fax: (510) 548-8046","webSite":"Website: "},{"name":"Adel M Fransis Dds Inc","street":"6040 Pacific Blvd ","cityState":"Huntington Park CA 90255-2931","phone":"Phone: (323) 583-5677","fax":"Fax: ","webSite":"Website: "},{"name":"Adel Shayegan Dmd Pc","street":"4203 E Indian School Rd # 220","cityState":"Phoenix AZ 85018-5359","phone":"Phone: (602) 955-1780","fax":"Fax: (602) 955-1153","webSite":"Website: "},{"name":"Adel, Douglas Michael","street":"14211 N.W. 150Th Ave ","cityState":"Alachua FL 32615-2047","phone":"Phone: (386) 462-4635","fax":"Fax: (386) 462-3009","webSite":"Website: "},{"name":"Adel, Kaveh Nasireddin","street":"612 E Ogden Ave ","cityState":"Naperville IL 60563-3237","phone":"Phone: (630) 369-8950","fax":"Fax: (630) 369-7342","webSite":"Website: "},{"name":"Adel, Sainy","street":"209 Nw Blue Pkwy ","cityState":"Lees Summit MO 64063-1872","phone":"Phone: (816) 287-8559","fax":"Fax: ","webSite":"Website: "},{"name":"Adela Agolli Tarshi Dmd P.C","street":"11 Cambridge St ","cityState":"Burlington MA 01803-4625","phone":"Phone: (781) 229-1111","fax":"Fax: ","webSite":"Website: "},{"name":"Adela Agolli Tarshi, D.M.D., P.C.","street":"131 Main St ","cityState":"Waltham MA 02453-6636","phone":"Phone: (781) 893-7500","fax":"Fax: ","webSite":"Website: "},{"name":"Adela Morocho, Dds, Llc","street":"344 University Blvd. West Suite 323","cityState":"Silver Spring MD 20901-1971","phone":"Phone: (301) 681-4900","fax":"Fax: (301) 681-8690","webSite":"Website: "},{"name":"Adela Slaton Dds Inc","street":"617 S Eighth St ","cityState":"El Centro CA 92243","phone":"Phone: (760) 312-5888","fax":"Fax: (760) 312-5918","webSite":"Website: "},{"name":"Adelaido A. Villarreal,Jr., D.D.S.","street":"2420 Pecan Blvd ","cityState":"Mcallen TX 78501-7334","phone":"Phone: (956) 682-6464","fax":"Fax: ","webSite":"Website: "},{"name":"Adelakun, Alaba","street":"4 S Hospital Dr ","cityState":"Murphysboro IL 62966-3333","phone":"Phone: (618) 985-8221","fax":"Fax: (618) 985-6860","webSite":"Website: "},{"name":"Adelante Healthcare-Surprise","street":"15351 W Bell Rd ","cityState":"Surprise AZ 85374-4580","phone":"Phone: (877) 809-5092","fax":"Fax: (623) 544-5119","webSite":"Website: "},{"name":"Adelberg Pediatric Dental Pc","street":"260 E Main St Suite 110","cityState":"Smithtown NY 11787-2982","phone":"Phone: (631) 360-7337","fax":"Fax: (631) 360-3815","webSite":"Website: "},{"name":"Adelberg, Marc T","street":"62 Lake Ave S Suite A","cityState":"Nesconset NY 11767-1094","phone":"Phone: (631) 360-7337","fax":"Fax: (631) 360-3815","webSite":"Website: "},{"name":"Adele Chambers D.M.D. P.C.","street":"668 Bedford St ","cityState":"Concord MA 01742-1905","phone":"Phone: (978) 287-1414","fax":"Fax: (978) 287-1414","webSite":"Website: "},{"name":"Adeleke, Funmi","street":"5722 S Pulaski Rd ","cityState":"Chicago IL 60629-4435","phone":"Phone: (773) 735-3440","fax":"Fax: (773) 735-5482","webSite":"Website: "},{"name":"Adeli Nadjafi, Nazila","street":"13651 Oxnard St ","cityState":"Van Nuys CA 91401-4045","phone":"Phone: (818) 908-3333","fax":"Fax: (818) 908-3334","webSite":"Website: "},{"name":"Adeli, Alex","street":"575 Boylston St Fl 7 ","cityState":"Boston MA 02116-3607","phone":"Phone: (617) 267-3889","fax":"Fax: ","webSite":"Website: "},{"name":"Adell, Lori","street":"903 S Kingshighway St ","cityState":"Sikeston MO 63801-4415","phone":"Phone: (573) 471-4167","fax":"Fax: (573) 472-4050","webSite":"Website: "},{"name":"Adelman, Daniel S","street":"2459 Ashby Ave ","cityState":"Berkeley CA 94705","phone":"Phone: (510) 548-4567","fax":"Fax: (510) 548-4568","webSite":"Website: "},{"name":"Adelman, David Michael","street":"16680 Ne 10Th Ave ","cityState":"North Miami Beach FL 33162","phone":"Phone: (305) 944-6669","fax":"Fax: (605) 944-6660","webSite":"Website: "},{"name":"Adelman, Edward Alfred","street":"7575 Cockrill Bend Road ","cityState":"Nashville TN 37209-0000","phone":"Phone: (615) 350-2700","fax":"Fax: (615) 350-2788","webSite":"Website: "},{"name":"Adelman, Laura","street":"9945 Vail Dr Suite 5","cityState":"Twinsburg OH 44087-4900","phone":"Phone: (330) 425-1885","fax":"Fax: (330) 425-1589","webSite":"Website: "},{"name":"Adelman, Robert Lee","street":"832 Germantown Pike ","cityState":"Plymouth Meeting PA 19462-2442","phone":"Phone: (610) 277-0996","fax":"Fax: (610) 275-5075","webSite":"Website: "},{"name":"Adelmann Dentistry Llc","street":"14247 Oconnell Ct 100","cityState":"Savage MN 55378-2878","phone":"Phone: (952) 226-3560","fax":"Fax: (952) 226-3562","webSite":"Website: "}]